{
    "meta": {
        "day": "20221231",
        "total": 4789080,
        "modified": "2023-02-19 17:05:37"
    },
    "data": {
        "南投縣": {
            "中寮鄉": 1371,
            "仁愛鄉": 3291,
            "信義鄉": 3141,
            "南投市": 18940,
            "名間鄉": 5253,
            "國姓鄉": 1871,
            "埔里鎮": 12774,
            "水里鄉": 1786,
            "竹山鎮": 7737,
            "草屯鎮": 17298,
            "集集鎮": 1094,
            "魚池鄉": 1264,
            "鹿谷鄉": 1723
        },
        "台中市": {
            "中區": 3285,
            "北區": 29688,
            "北屯區": 54314,
            "南區": 26141,
            "南屯區": 35017,
            "后里區": 9366,
            "和平區": 1591,
            "外埔區": 6155,
            "大安區": 3267,
            "大甲區": 14327,
            "大肚區": 11516,
            "大里區": 43593,
            "大雅區": 21362,
            "太平區": 40428,
            "新社區": 2708,
            "東勢區": 7128,
            "東區": 15810,
            "梧棲區": 14581,
            "沙鹿區": 22373,
            "清水區": 17965,
            "潭子區": 21209,
            "烏日區": 16962,
            "石岡區": 2112,
            "神岡區": 13370,
            "西區": 20844,
            "西屯區": 50243,
            "豐原區": 29836,
            "霧峰區": 13707,
            "龍井區": 16573
        },
        "台北市": {
            "中山區": 42946,
            "中正區": 22339,
            "信義區": 42073,
            "內湖區": 49971,
            "北投區": 47924,
            "南港區": 24363,
            "士林區": 48545,
            "大同區": 23939,
            "大安區": 40366,
            "文山區": 48987,
            "松山區": 31599,
            "萬華區": 39714
        },
        "台南市": {
            "七股區": 2623,
            "下營區": 3043,
            "中西區": 12117,
            "仁德區": 16574,
            "佳里區": 8885,
            "六甲區": 3476,
            "北區": 23583,
            "北門區": 800,
            "南化區": 733,
            "南區": 23540,
            "善化區": 9884,
            "大內區": 1004,
            "學甲區": 3108,
            "安南區": 38492,
            "安定區": 5285,
            "安平區": 12043,
            "官田區": 3447,
            "將軍區": 1869,
            "山上區": 1446,
            "左鎮區": 496,
            "後壁區": 2810,
            "新化區": 7950,
            "新市區": 8518,
            "新營區": 12817,
            "東區": 30232,
            "東山區": 1935,
            "柳營區": 3685,
            "楠西區": 845,
            "歸仁區": 13320,
            "永康區": 52578,
            "玉井區": 1878,
            "白河區": 3201,
            "西港區": 3847,
            "關廟區": 6624,
            "鹽水區": 3700,
            "麻豆區": 6726,
            "龍崎區": 290
        },
        "台東縣": {
            "卑南鄉": 3195,
            "台東市": 24907,
            "大武鄉": 765,
            "太麻里鄉": 1823,
            "延平鄉": 947,
            "成功鎮": 2223,
            "東河鄉": 1155,
            "池上鄉": 1016,
            "海端鄉": 1169,
            "綠島鄉": 628,
            "蘭嶼鄉": 1243,
            "達仁鄉": 541,
            "金峰鄉": 738,
            "長濱鄉": 899,
            "關山鎮": 1339,
            "鹿野鄉": 1315
        },
        "嘉義市": {
            "東區": 19176,
            "西區": 24378
        },
        "嘉義縣": {
            "中埔鄉": 6674,
            "六腳鄉": 2414,
            "大埔鄉": 201,
            "大林鎮": 4935,
            "太保市": 6385,
            "布袋鎮": 2531,
            "新港鄉": 4034,
            "朴子市": 6129,
            "東石鄉": 1915,
            "梅山鄉": 1934,
            "民雄鄉": 12778,
            "水上鄉": 8508,
            "溪口鄉": 1667,
            "番路鄉": 1190,
            "竹崎鄉": 4065,
            "義竹鄉": 1324,
            "阿里山鄉": 822,
            "鹿草鄉": 1880
        },
        "基隆市": {
            "七堵區": 14094,
            "中山區": 11234,
            "中正區": 13842,
            "仁愛區": 9640,
            "信義區": 13948,
            "其他": 1,
            "安樂區": 21818,
            "暖暖區": 9782
        },
        "宜蘭縣": {
            "三星鄉": 4248,
            "五結鄉": 8649,
            "冬山鄉": 12407,
            "南澳鄉": 2342,
            "員山鄉": 6653,
            "壯圍鄉": 4570,
            "大同鄉": 1796,
            "宜蘭市": 19910,
            "礁溪鄉": 7576,
            "羅東鎮": 14021,
            "蘇澳鎮": 9034,
            "頭城鎮": 5272
        },
        "屏東縣": {
            "三地門鄉": 1626,
            "九如鄉": 3797,
            "佳冬鄉": 2202,
            "來義鄉": 1948,
            "內埔鄉": 10341,
            "南州鄉": 1436,
            "屏東市": 36910,
            "崁頂鄉": 1746,
            "恆春鎮": 5800,
            "新園鄉": 6391,
            "新埤鄉": 1356,
            "春日鄉": 1343,
            "東港鎮": 9642,
            "枋寮鄉": 3901,
            "枋山鄉": 545,
            "林邊鄉": 2186,
            "泰武鄉": 1800,
            "滿州鄉": 841,
            "潮州鎮": 10178,
            "牡丹鄉": 896,
            "獅子鄉": 983,
            "琉球鄉": 1608,
            "瑪家鄉": 1905,
            "竹田鄉": 3699,
            "萬丹鄉": 9616,
            "萬巒鄉": 2981,
            "車城鄉": 1225,
            "里港鄉": 4016,
            "長治鄉": 6142,
            "霧台鄉": 352,
            "高樹鄉": 2576,
            "鹽埔鄉": 4269,
            "麟洛鄉": 1822
        },
        "彰化縣": {
            "二林鎮": 8688,
            "二水鄉": 2017,
            "伸港鄉": 7631,
            "北斗鎮": 5866,
            "和美鎮": 19870,
            "員林市": 21483,
            "埔心鄉": 6293,
            "埔鹽鄉": 4963,
            "埤頭鄉": 4557,
            "大城鄉": 2020,
            "大村鄉": 7925,
            "彰化市": 44181,
            "永靖鄉": 5379,
            "溪州鄉": 4084,
            "溪湖鎮": 8944,
            "田中鎮": 6927,
            "田尾鄉": 3594,
            "社頭鄉": 6850,
            "福興鄉": 8804,
            "秀水鄉": 7048,
            "竹塘鄉": 1771,
            "線西鄉": 3321,
            "芬園鄉": 3888,
            "花壇鄉": 9309,
            "芳苑鄉": 5117,
            "鹿港鎮": 19949
        },
        "新北市": {
            "三峽區": 26996,
            "三芝區": 3426,
            "三重區": 110778,
            "中和區": 113001,
            "五股區": 24589,
            "八里區": 9397,
            "土城區": 62583,
            "坪林區": 523,
            "平溪區": 397,
            "新店區": 72763,
            "新莊區": 111528,
            "板橋區": 144008,
            "林口區": 26863,
            "樹林區": 43887,
            "永和區": 50988,
            "汐止區": 60306,
            "泰山區": 20204,
            "淡水區": 42182,
            "深坑區": 6600,
            "烏來區": 963,
            "瑞芳區": 7807,
            "石碇區": 882,
            "石門區": 809,
            "萬里區": 2938,
            "蘆洲區": 51735,
            "貢寮區": 965,
            "金山區": 3472,
            "雙溪區": 763,
            "鶯歌區": 21699
        },
        "新竹市": {
            "北區": 29497,
            "東區": 45819,
            "香山區": 17223
        },
        "新竹縣": {
            "五峰鄉": 805,
            "北埔鄉": 1181,
            "寶山鄉": 2974,
            "尖石鄉": 1866,
            "峨眉鄉": 548,
            "新埔鎮": 6183,
            "新豐鄉": 13410,
            "橫山鄉": 2010,
            "湖口鄉": 23001,
            "竹北市": 42742,
            "竹東鎮": 22082,
            "芎林鄉": 3767,
            "關西鎮": 4995
        },
        "桃園市": {
            "中壢區": 98314,
            "八德區": 50223,
            "大園區": 20022,
            "大溪區": 22345,
            "平鎮區": 51683,
            "復興區": 2289,
            "新屋區": 10187,
            "桃園區": 106915,
            "楊梅區": 40130,
            "蘆竹區": 42135,
            "觀音區": 17202,
            "龍潭區": 27415,
            "龜山區": 48735
        },
        "澎湖縣": {
            "七美鄉": 213,
            "望安鄉": 208,
            "湖西鄉": 2174,
            "白沙鄉": 854,
            "西嶼鄉": 806,
            "馬公市": 10129
        },
        "花蓮縣": {
            "光復鄉": 2185,
            "卓溪鄉": 1480,
            "吉安鄉": 22033,
            "壽豐鄉": 4097,
            "富里鄉": 1566,
            "新城鄉": 6374,
            "玉里鎮": 5537,
            "瑞穗鄉": 1714,
            "秀林鄉": 5546,
            "花蓮市": 22269,
            "萬榮鄉": 1690,
            "豐濱鄉": 627,
            "鳳林鎮": 1834
        },
        "苗栗縣": {
            "三灣鄉": 897,
            "三義鄉": 2343,
            "公館鄉": 4914,
            "卓蘭鎮": 1716,
            "南庄鄉": 1419,
            "大湖鄉": 1456,
            "後龍鎮": 5951,
            "泰安鄉": 1197,
            "獅潭鄉": 336,
            "竹南鎮": 20383,
            "苑裡鎮": 8243,
            "苗栗市": 16220,
            "西湖鄉": 691,
            "通霄鎮": 5079,
            "造橋鄉": 2969,
            "銅鑼鄉": 2345,
            "頭份市": 21906,
            "頭屋鄉": 1739
        },
        "連江縣": {
            "北竿鄉": 334,
            "南竿鄉": 1249,
            "東引鄉": 333,
            "莒光鄉": 163
        },
        "金門縣": {
            "烈嶼鄉": 498,
            "烏坵鄉": 11,
            "金城鎮": 3112,
            "金寧鄉": 3027,
            "金沙鎮": 1398,
            "金湖鎮": 2887
        },
        "雲林縣": {
            "二崙鄉": 2892,
            "元長鄉": 2695,
            "北港鎮": 5069,
            "口湖鄉": 2148,
            "古坑鄉": 3866,
            "台西鄉": 2343,
            "四湖鄉": 1892,
            "土庫鎮": 3619,
            "大埤鄉": 2354,
            "崙背鄉": 3093,
            "斗六市": 19983,
            "斗南鎮": 7133,
            "東勢鄉": 1350,
            "林內鄉": 2248,
            "水林鄉": 2047,
            "莿桐鄉": 4257,
            "虎尾鎮": 13454,
            "褒忠鄉": 1648,
            "西螺鎮": 7440,
            "麥寮鄉": 5305
        },
        "高雄市": {
            "三民區": 61660,
            "仁武區": 21055,
            "內門區": 1565,
            "六龜區": 1438,
            "前金區": 7613,
            "前鎮區": 38376,
            "大寮區": 26979,
            "大樹區": 7736,
            "大社區": 7517,
            "小港區": 34396,
            "岡山區": 19926,
            "左營區": 36790,
            "彌陀區": 3523,
            "新興區": 8971,
            "旗山區": 4917,
            "旗津區": 5251,
            "杉林區": 1379,
            "林園區": 13621,
            "桃源區": 940,
            "梓官區": 7555,
            "楠梓區": 41999,
            "橋頭區": 7428,
            "永安區": 2014,
            "湖內區": 5721,
            "燕巢區": 8004,
            "田寮區": 766,
            "甲仙區": 426,
            "美濃區": 4198,
            "苓雅區": 30982,
            "茂林區": 420,
            "茄萣區": 5386,
            "路竹區": 10109,
            "那瑪夏區": 609,
            "阿蓮區": 5002,
            "鳥松區": 8285,
            "鳳山區": 75305,
            "鹽埕區": 4029,
            "鼓山區": 26029
        }
    },
    "rate": {
        "南投縣": {
            "中寮鄉": -0.47,
            "仁愛鄉": -0.3,
            "信義鄉": -0.35,
            "南投市": -0.46,
            "名間鄉": -0.48,
            "國姓鄉": -0.45,
            "埔里鎮": -0.47,
            "水里鄉": -0.53,
            "竹山鎮": -0.46,
            "草屯鎮": -0.49,
            "集集鎮": -0.52,
            "魚池鄉": -0.54,
            "鹿谷鄉": -0.47
        },
        "台中市": {
            "中區": -0.41,
            "北區": -0.5,
            "北屯區": -0.51,
            "南區": -0.51,
            "南屯區": -0.5,
            "后里區": -0.49,
            "和平區": -0.39,
            "外埔區": -0.47,
            "大安區": -0.44,
            "大甲區": -0.43,
            "大肚區": -0.44,
            "大里區": -0.46,
            "大雅區": -0.44,
            "太平區": -0.46,
            "新社區": -0.54,
            "東勢區": -0.49,
            "東區": -0.46,
            "梧棲區": -0.41,
            "沙鹿區": -0.47,
            "清水區": -0.45,
            "潭子區": -0.49,
            "烏日區": -0.45,
            "石岡區": -0.47,
            "神岡區": -0.44,
            "西區": -0.49,
            "西屯區": -0.5,
            "豐原區": -0.48,
            "霧峰區": -0.45,
            "龍井區": -0.46
        },
        "台北市": {
            "中山區": -0.48,
            "中正區": -0.49,
            "信義區": -0.46,
            "內湖區": -0.5,
            "北投區": -0.45,
            "南港區": -0.46,
            "士林區": -0.48,
            "大同區": -0.44,
            "大安區": -0.51,
            "文山區": -0.49,
            "松山區": -0.5,
            "萬華區": -0.38
        },
        "台南市": {
            "七股區": -0.44,
            "下營區": -0.46,
            "中西區": -0.46,
            "仁德區": -0.46,
            "佳里區": -0.48,
            "六甲區": -0.45,
            "北區": -0.48,
            "北門區": -0.5,
            "南化區": -0.44,
            "南區": -0.42,
            "善化區": -0.52,
            "大內區": -0.46,
            "學甲區": -0.48,
            "安南區": -0.45,
            "安定區": -0.46,
            "安平區": -0.48,
            "官田區": -0.46,
            "將軍區": -0.49,
            "山上區": -0.39,
            "左鎮區": -0.4,
            "後壁區": -0.5,
            "新化區": -0.44,
            "新市區": -0.49,
            "新營區": -0.48,
            "東區": -0.5,
            "東山區": -0.52,
            "柳營區": -0.42,
            "楠西區": -0.45,
            "歸仁區": -0.44,
            "永康區": -0.46,
            "玉井區": -0.4,
            "白河區": -0.45,
            "西港區": -0.46,
            "關廟區": -0.4,
            "鹽水區": -0.44,
            "麻豆區": -0.49,
            "龍崎區": -0.37
        },
        "台東縣": {
            "卑南鄉": -0.41,
            "台東市": -0.41,
            "大武鄉": -0.4,
            "太麻里鄉": -0.4,
            "延平鄉": -0.23,
            "成功鎮": -0.37,
            "東河鄉": -0.4,
            "池上鄉": -0.44,
            "海端鄉": -0.21,
            "綠島鄉": -0.32,
            "蘭嶼鄉": -0.18,
            "達仁鄉": -0.44,
            "金峰鄉": -0.44,
            "長濱鄉": -0.32,
            "關山鎮": -0.41,
            "鹿野鄉": -0.32
        },
        "嘉義市": {
            "東區": -0.5,
            "西區": -0.49
        },
        "嘉義縣": {
            "中埔鄉": -0.5,
            "六腳鄉": -0.49,
            "大埔鄉": -0.47,
            "大林鎮": -0.46,
            "太保市": -0.49,
            "布袋鎮": -0.44,
            "新港鄉": -0.48,
            "朴子市": -0.48,
            "東石鄉": -0.45,
            "梅山鄉": -0.47,
            "民雄鄉": -0.51,
            "水上鄉": -0.45,
            "溪口鄉": -0.5,
            "番路鄉": -0.5,
            "竹崎鄉": -0.5,
            "義竹鄉": -0.51,
            "阿里山鄉": -0.46,
            "鹿草鄉": -0.43
        },
        "基隆市": {
            "七堵區": -0.4,
            "中山區": -0.4,
            "中正區": -0.39,
            "仁愛區": -0.37,
            "信義區": -0.41,
            "其他": 0,
            "安樂區": -0.42,
            "暖暖區": -0.43
        },
        "宜蘭縣": {
            "三星鄉": -0.45,
            "五結鄉": -0.47,
            "冬山鄉": -0.45,
            "南澳鄉": -0.19,
            "員山鄉": -0.46,
            "壯圍鄉": -0.47,
            "大同鄉": -0.22,
            "宜蘭市": -0.47,
            "礁溪鄉": -0.44,
            "羅東鎮": -0.46,
            "蘇澳鎮": -0.38,
            "頭城鎮": -0.42
        },
        "屏東縣": {
            "三地門鄉": -0.36,
            "九如鄉": -0.42,
            "佳冬鄉": -0.45,
            "來義鄉": -0.37,
            "內埔鄉": -0.44,
            "南州鄉": -0.46,
            "屏東市": -0.43,
            "崁頂鄉": -0.43,
            "恆春鎮": -0.38,
            "新園鄉": -0.38,
            "新埤鄉": -0.44,
            "春日鄉": -0.3,
            "東港鎮": -0.36,
            "枋寮鄉": -0.39,
            "枋山鄉": -0.44,
            "林邊鄉": -0.45,
            "泰武鄉": -0.26,
            "滿州鄉": -0.38,
            "潮州鎮": -0.44,
            "牡丹鄉": -0.46,
            "獅子鄉": -0.37,
            "琉球鄉": -0.32,
            "瑪家鄉": -0.34,
            "竹田鄉": -0.37,
            "萬丹鄉": -0.42,
            "萬巒鄉": -0.43,
            "車城鄉": -0.4,
            "里港鄉": -0.42,
            "長治鄉": -0.43,
            "霧台鄉": -0.45,
            "高樹鄉": -0.47,
            "鹽埔鄉": -0.39,
            "麟洛鄉": -0.45
        },
        "彰化縣": {
            "二林鎮": -0.41,
            "二水鄉": -0.45,
            "伸港鄉": -0.43,
            "北斗鎮": -0.46,
            "和美鎮": -0.44,
            "員林市": -0.48,
            "埔心鄉": -0.47,
            "埔鹽鄉": -0.47,
            "埤頭鄉": -0.45,
            "大城鄉": -0.39,
            "大村鄉": -0.44,
            "彰化市": -0.47,
            "永靖鄉": -0.49,
            "溪州鄉": -0.45,
            "溪湖鎮": -0.46,
            "田中鎮": -0.44,
            "田尾鄉": -0.5,
            "社頭鄉": -0.48,
            "福興鄉": -0.45,
            "秀水鄉": -0.48,
            "竹塘鄉": -0.44,
            "線西鄉": -0.43,
            "芬園鄉": -0.44,
            "花壇鄉": -0.45,
            "芳苑鄉": -0.4,
            "鹿港鎮": -0.4
        },
        "新北市": {
            "三峽區": -0.43,
            "三芝區": -0.48,
            "三重區": -0.41,
            "中和區": -0.43,
            "五股區": -0.44,
            "八里區": -0.44,
            "土城區": -0.42,
            "坪林區": -0.47,
            "平溪區": -0.46,
            "新店區": -0.47,
            "新莊區": -0.42,
            "板橋區": -0.43,
            "林口區": -0.5,
            "樹林區": -0.42,
            "永和區": -0.47,
            "汐止區": -0.44,
            "泰山區": -0.44,
            "淡水區": -0.5,
            "深坑區": -0.45,
            "烏來區": -0.34,
            "瑞芳區": -0.38,
            "石碇區": -0.42,
            "石門區": -0.42,
            "萬里區": -0.36,
            "蘆洲區": -0.44,
            "貢寮區": -0.4,
            "金山區": -0.37,
            "雙溪區": -0.45,
            "鶯歌區": -0.43
        },
        "新竹市": {
            "北區": -0.52,
            "東區": -0.54,
            "香山區": -0.5
        },
        "新竹縣": {
            "五峰鄉": -0.27,
            "北埔鄉": -0.5,
            "寶山鄉": -0.49,
            "尖石鄉": -0.29,
            "峨眉鄉": -0.52,
            "新埔鎮": -0.49,
            "新豐鄉": -0.45,
            "橫山鄉": -0.47,
            "湖口鄉": -0.4,
            "竹北市": -0.54,
            "竹東鎮": -0.47,
            "芎林鄉": -0.5,
            "關西鎮": -0.45
        },
        "桃園市": {
            "中壢區": -0.46,
            "八德區": -0.43,
            "大園區": -0.42,
            "大溪區": -0.4,
            "平鎮區": -0.45,
            "復興區": -0.33,
            "新屋區": -0.43,
            "桃園區": -0.45,
            "楊梅區": -0.45,
            "蘆竹區": -0.45,
            "觀音區": -0.41,
            "龍潭區": -0.44,
            "龜山區": -0.44
        },
        "澎湖縣": {
            "七美鄉": -0.3,
            "望安鄉": -0.24,
            "湖西鄉": -0.45,
            "白沙鄉": -0.41,
            "西嶼鄉": -0.4,
            "馬公市": -0.44
        },
        "花蓮縣": {
            "光復鄉": -0.38,
            "卓溪鄉": -0.27,
            "吉安鄉": -0.44,
            "壽豐鄉": -0.47,
            "富里鄉": -0.35,
            "新城鄉": -0.38,
            "玉里鎮": -0.4,
            "瑞穗鄉": -0.39,
            "秀林鄉": -0.23,
            "花蓮市": -0.47,
            "萬榮鄉": -0.23,
            "豐濱鄉": -0.33,
            "鳳林鎮": -0.39
        },
        "苗栗縣": {
            "三灣鄉": -0.49,
            "三義鄉": -0.53,
            "公館鄉": -0.55,
            "卓蘭鎮": -0.51,
            "南庄鄉": -0.41,
            "大湖鄉": -0.55,
            "後龍鎮": -0.47,
            "泰安鄉": -0.37,
            "獅潭鄉": -0.53,
            "竹南鎮": -0.48,
            "苑裡鎮": -0.46,
            "苗栗市": -0.51,
            "西湖鄉": -0.52,
            "通霄鎮": -0.44,
            "造橋鄉": -0.43,
            "銅鑼鄉": -0.53,
            "頭份市": -0.51,
            "頭屋鄉": -0.47
        },
        "連江縣": {
            "北竿鄉": -0.41,
            "南竿鄉": -0.44,
            "東引鄉": -0.47,
            "莒光鄉": -0.37
        },
        "金門縣": {
            "烈嶼鄉": -0.6,
            "烏坵鄉": -0.65,
            "金城鎮": -0.52,
            "金寧鄉": -0.53,
            "金沙鎮": -0.52,
            "金湖鎮": -0.51
        },
        "雲林縣": {
            "二崙鄉": -0.44,
            "元長鄉": -0.48,
            "北港鎮": -0.5,
            "口湖鄉": -0.49,
            "古坑鄉": -0.48,
            "台西鄉": -0.47,
            "四湖鄉": -0.45,
            "土庫鎮": -0.51,
            "大埤鄉": -0.48,
            "崙背鄉": -0.45,
            "斗六市": -0.51,
            "斗南鎮": -0.46,
            "東勢鄉": -0.52,
            "林內鄉": -0.5,
            "水林鄉": -0.47,
            "莿桐鄉": -0.46,
            "虎尾鎮": -0.5,
            "褒忠鄉": -0.45,
            "西螺鎮": -0.4,
            "麥寮鄉": -0.47
        },
        "高雄市": {
            "三民區": -0.49,
            "仁武區": -0.45,
            "內門區": -0.47,
            "六龜區": -0.38,
            "前金區": -0.36,
            "前鎮區": -0.41,
            "大寮區": -0.39,
            "大樹區": -0.41,
            "大社區": -0.45,
            "小港區": -0.39,
            "岡山區": -0.45,
            "左營區": -0.48,
            "彌陀區": -0.4,
            "新興區": -0.44,
            "旗山區": -0.48,
            "旗津區": -0.35,
            "杉林區": -0.44,
            "林園區": -0.4,
            "桃源區": -0.28,
            "梓官區": -0.38,
            "楠梓區": -0.45,
            "橋頭區": -0.49,
            "永安區": -0.43,
            "湖內區": -0.45,
            "燕巢區": -0.38,
            "田寮區": -0.45,
            "甲仙區": -0.48,
            "美濃區": -0.51,
            "苓雅區": -0.43,
            "茂林區": -0.39,
            "茄萣區": -0.4,
            "路竹區": -0.43,
            "那瑪夏區": -0.36,
            "阿蓮區": -0.41,
            "鳥松區": -0.46,
            "鳳山區": -0.43,
            "鹽埕區": -0.45,
            "鼓山區": -0.46
        }
    },
    "increase": {
        "南投縣": {
            "中寮鄉": -1237,
            "仁愛鄉": -1433,
            "信義鄉": -1671,
            "南投市": -15995,
            "名間鄉": -4814,
            "國姓鄉": -1548,
            "埔里鎮": -11131,
            "水里鄉": -1980,
            "竹山鎮": -6635,
            "草屯鎮": -16708,
            "集集鎮": -1206,
            "魚池鄉": -1465,
            "鹿谷鄉": -1525
        },
        "台中市": {
            "中區": -2325,
            "北區": -29450,
            "北屯區": -56836,
            "南區": -27251,
            "南屯區": -35505,
            "后里區": -9095,
            "和平區": -1000,
            "外埔區": -5420,
            "大安區": -2569,
            "大甲區": -10829,
            "大肚區": -8992,
            "大里區": -37882,
            "大雅區": -17111,
            "太平區": -34792,
            "新社區": -3162,
            "東勢區": -6905,
            "東區": -13213,
            "梧棲區": -10023,
            "沙鹿區": -19972,
            "清水區": -14856,
            "潭子區": -20360,
            "烏日區": -13687,
            "石岡區": -1845,
            "神岡區": -10571,
            "西區": -20361,
            "西屯區": -50059,
            "豐原區": -27194,
            "霧峰區": -11214,
            "龍井區": -14386
        },
        "台北市": {
            "中山區": -38924,
            "中正區": -21894,
            "信義區": -36280,
            "內湖區": -50021,
            "北投區": -38749,
            "南港區": -20475,
            "士林區": -44282,
            "大同區": -18955,
            "大安區": -42804,
            "文山區": -46292,
            "松山區": -31386,
            "萬華區": -24750
        },
        "台南市": {
            "七股區": -2052,
            "下營區": -2545,
            "中西區": -10374,
            "仁德區": -13928,
            "佳里區": -8214,
            "六甲區": -2887,
            "北區": -21365,
            "北門區": -800,
            "南化區": -586,
            "南區": -17371,
            "善化區": -10659,
            "大內區": -863,
            "學甲區": -2824,
            "安南區": -31004,
            "安定區": -4593,
            "安平區": -10935,
            "官田區": -2990,
            "將軍區": -1818,
            "山上區": -932,
            "左鎮區": -328,
            "後壁區": -2803,
            "新化區": -6159,
            "新市區": -8261,
            "新營區": -11685,
            "東區": -29955,
            "東山區": -2089,
            "柳營區": -2721,
            "楠西區": -686,
            "歸仁區": -10648,
            "永康區": -44164,
            "玉井區": -1230,
            "白河區": -2653,
            "西港區": -3295,
            "關廟區": -4356,
            "鹽水區": -2878,
            "麻豆區": -6439,
            "龍崎區": -168
        },
        "台東縣": {
            "卑南鄉": -2256,
            "台東市": -17487,
            "大武鄉": -506,
            "太麻里鄉": -1216,
            "延平鄉": -290,
            "成功鎮": -1282,
            "東河鄉": -755,
            "池上鄉": -813,
            "海端鄉": -320,
            "綠島鄉": -292,
            "蘭嶼鄉": -276,
            "達仁鄉": -418,
            "金峰鄉": -591,
            "長濱鄉": -420,
            "關山鎮": -937,
            "鹿野鄉": -611
        },
        "嘉義市": {
            "東區": -19089,
            "西區": -22973
        },
        "嘉義縣": {
            "中埔鄉": -6780,
            "六腳鄉": -2284,
            "大埔鄉": -179,
            "大林鎮": -4207,
            "太保市": -6132,
            "布袋鎮": -2008,
            "新港鄉": -3703,
            "朴子市": -5707,
            "東石鄉": -1574,
            "梅山鄉": -1714,
            "民雄鄉": -13337,
            "水上鄉": -7016,
            "溪口鄉": -1653,
            "番路鄉": -1181,
            "竹崎鄉": -4092,
            "義竹鄉": -1388,
            "阿里山鄉": -706,
            "鹿草鄉": -1440
        },
        "基隆市": {
            "七堵區": -9419,
            "中山區": -7531,
            "中正區": -8864,
            "仁愛區": -5731,
            "信義區": -9706,
            "其他": 0,
            "安樂區": -15964,
            "暖暖區": -7268
        },
        "宜蘭縣": {
            "三星鄉": -3470,
            "五結鄉": -7717,
            "冬山鄉": -10121,
            "南澳鄉": -554,
            "員山鄉": -5577,
            "壯圍鄉": -4063,
            "大同鄉": -507,
            "宜蘭市": -17765,
            "礁溪鄉": -6051,
            "羅東鎮": -11753,
            "蘇澳鎮": -5456,
            "頭城鎮": -3848
        },
        "屏東縣": {
            "三地門鄉": -913,
            "九如鄉": -2711,
            "佳冬鄉": -1821,
            "來義鄉": -1138,
            "內埔鄉": -8081,
            "南州鄉": -1245,
            "屏東市": -28372,
            "崁頂鄉": -1325,
            "恆春鎮": -3552,
            "新園鄉": -3973,
            "新埤鄉": -1082,
            "春日鄉": -571,
            "東港鎮": -5346,
            "枋寮鄉": -2493,
            "枋山鄉": -434,
            "林邊鄉": -1781,
            "泰武鄉": -622,
            "滿州鄉": -524,
            "潮州鎮": -7984,
            "牡丹鄉": -749,
            "獅子鄉": -579,
            "琉球鄉": -769,
            "瑪家鄉": -985,
            "竹田鄉": -2175,
            "萬丹鄉": -6987,
            "萬巒鄉": -2275,
            "車城鄉": -826,
            "里港鄉": -2874,
            "長治鄉": -4571,
            "霧台鄉": -288,
            "高樹鄉": -2318,
            "鹽埔鄉": -2756,
            "麟洛鄉": -1505
        },
        "彰化縣": {
            "二林鎮": -6087,
            "二水鄉": -1633,
            "伸港鄉": -5827,
            "北斗鎮": -5036,
            "和美鎮": -15527,
            "員林市": -19852,
            "埔心鄉": -5574,
            "埔鹽鄉": -4483,
            "埤頭鄉": -3753,
            "大城鄉": -1299,
            "大村鄉": -6212,
            "彰化市": -38932,
            "永靖鄉": -5198,
            "溪州鄉": -3316,
            "溪湖鎮": -7607,
            "田中鎮": -5444,
            "田尾鄉": -3567,
            "社頭鄉": -6361,
            "福興鄉": -7115,
            "秀水鄉": -6471,
            "竹塘鄉": -1395,
            "線西鄉": -2456,
            "芬園鄉": -3085,
            "花壇鄉": -7542,
            "芳苑鄉": -3416,
            "鹿港鎮": -13338
        },
        "新北市": {
            "三峽區": -20775,
            "三芝區": -3137,
            "三重區": -77520,
            "中和區": -86871,
            "五股區": -19148,
            "八里區": -7482,
            "土城區": -46226,
            "坪林區": -472,
            "平溪區": -338,
            "新店區": -65005,
            "新莊區": -81441,
            "板橋區": -108080,
            "林口區": -26939,
            "樹林區": -31771,
            "永和區": -45700,
            "汐止區": -48342,
            "泰山區": -15938,
            "淡水區": -42029,
            "深坑區": -5453,
            "烏來區": -488,
            "瑞芳區": -4722,
            "石碇區": -645,
            "石門區": -595,
            "萬里區": -1671,
            "蘆洲區": -40962,
            "貢寮區": -645,
            "金山區": -2025,
            "雙溪區": -612,
            "鶯歌區": -16376
        },
        "新竹市": {
            "北區": -31370,
            "東區": -53522,
            "香山區": -17455
        },
        "新竹縣": {
            "五峰鄉": -297,
            "北埔鄉": -1164,
            "寶山鄉": -2901,
            "尖石鄉": -774,
            "峨眉鄉": -591,
            "新埔鎮": -5875,
            "新豐鄉": -11006,
            "橫山鄉": -1762,
            "湖口鄉": -15077,
            "竹北市": -49851,
            "竹東鎮": -19864,
            "芎林鄉": -3794,
            "關西鎮": -4103
        },
        "桃園市": {
            "中壢區": -84188,
            "八德區": -38156,
            "大園區": -14641,
            "大溪區": -14727,
            "平鎮區": -42920,
            "復興區": -1103,
            "新屋區": -7552,
            "桃園區": -87415,
            "楊梅區": -32423,
            "蘆竹區": -33894,
            "觀音區": -12091,
            "龍潭區": -21562,
            "龜山區": -37892
        },
        "澎湖縣": {
            "七美鄉": -93,
            "望安鄉": -67,
            "湖西鄉": -1767,
            "白沙鄉": -589,
            "西嶼鄉": -548,
            "馬公市": -7811
        },
        "花蓮縣": {
            "光復鄉": -1342,
            "卓溪鄉": -553,
            "吉安鄉": -17517,
            "壽豐鄉": -3581,
            "富里鄉": -848,
            "新城鄉": -3923,
            "玉里鎮": -3621,
            "瑞穗鄉": -1109,
            "秀林鄉": -1614,
            "花蓮市": -19481,
            "萬榮鄉": -504,
            "豐濱鄉": -304,
            "鳳林鎮": -1152
        },
        "苗栗縣": {
            "三灣鄉": -854,
            "三義鄉": -2652,
            "公館鄉": -6062,
            "卓蘭鎮": -1759,
            "南庄鄉": -993,
            "大湖鄉": -1749,
            "後龍鎮": -5368,
            "泰安鄉": -697,
            "獅潭鄉": -384,
            "竹南鎮": -18993,
            "苑裡鎮": -7100,
            "苗栗市": -17058,
            "西湖鄉": -756,
            "通霄鎮": -3916,
            "造橋鄉": -2255,
            "銅鑼鄉": -2655,
            "頭份市": -22419,
            "頭屋鄉": -1518
        },
        "連江縣": {
            "北竿鄉": -232,
            "南竿鄉": -972,
            "東引鄉": -300,
            "莒光鄉": -95
        },
        "金門縣": {
            "烈嶼鄉": -733,
            "烏坵鄉": -20,
            "金城鎮": -3392,
            "金寧鄉": -3403,
            "金沙鎮": -1488,
            "金湖鎮": -2968
        },
        "雲林縣": {
            "二崙鄉": -2284,
            "元長鄉": -2507,
            "北港鎮": -5039,
            "口湖鄉": -2092,
            "古坑鄉": -3622,
            "台西鄉": -2044,
            "四湖鄉": -1549,
            "土庫鎮": -3793,
            "大埤鄉": -2195,
            "崙背鄉": -2503,
            "斗六市": -20696,
            "斗南鎮": -6193,
            "東勢鄉": -1484,
            "林內鄉": -2280,
            "水林鄉": -1824,
            "莿桐鄉": -3585,
            "虎尾鎮": -13415,
            "褒忠鄉": -1372,
            "西螺鎮": -5046,
            "麥寮鄉": -4730
        },
        "高雄市": {
            "三民區": -58748,
            "仁武區": -17154,
            "內門區": -1415,
            "六龜區": -898,
            "前金區": -4233,
            "前鎮區": -27206,
            "大寮區": -17276,
            "大樹區": -5475,
            "大社區": -6092,
            "小港區": -22343,
            "岡山區": -16376,
            "左營區": -34272,
            "彌陀區": -2308,
            "新興區": -7123,
            "旗山區": -4630,
            "旗津區": -2799,
            "杉林區": -1101,
            "林園區": -9065,
            "桃源區": -363,
            "梓官區": -4681,
            "楠梓區": -34641,
            "橋頭區": -7078,
            "永安區": -1534,
            "湖內區": -4686,
            "燕巢區": -4886,
            "田寮區": -630,
            "甲仙區": -392,
            "美濃區": -4299,
            "苓雅區": -23563,
            "茂林區": -271,
            "茄萣區": -3615,
            "路竹區": -7692,
            "那瑪夏區": -340,
            "阿蓮區": -3534,
            "鳥松區": -6949,
            "鳳山區": -57433,
            "鹽埕區": -3256,
            "鼓山區": -22598
        }
    },
    "avg7": {
        "南投縣": {
            "中寮鄉": 566,
            "仁愛鄉": 1139.43,
            "信義鄉": 1134.29,
            "南投市": 7657.57,
            "名間鄉": 2176.43,
            "國姓鄉": 754,
            "埔里鎮": 5212,
            "水里鄉": 791,
            "竹山鎮": 3143.29,
            "草屯鎮": 7285,
            "集集鎮": 481.86,
            "魚池鄉": 566.57,
            "鹿谷鄉": 706.71
        },
        "台中市": {
            "中區": 1264,
            "北區": 12598.14,
            "北屯區": 23467.29,
            "南區": 11274.71,
            "南屯區": 14963.71,
            "后里區": 3953.29,
            "和平區": 595,
            "外埔區": 2522,
            "大安區": 1294.57,
            "大甲區": 5604.86,
            "大肚區": 4548.14,
            "大里區": 17770.71,
            "大雅區": 8491.43,
            "太平區": 16426.14,
            "新社區": 1218.29,
            "東勢區": 3008.86,
            "東區": 6364.71,
            "梧棲區": 5568.71,
            "沙鹿區": 9192.43,
            "清水區": 7202.71,
            "潭子區": 8910,
            "烏日區": 6763.43,
            "石岡區": 862.43,
            "神岡區": 5303.29,
            "西區": 8801.71,
            "西屯區": 21340.43,
            "豐原區": 12343.43,
            "霧峰區": 5489,
            "龍井區": 6744.43
        },
        "台北市": {
            "中山區": 17706.14,
            "中正區": 9431.14,
            "信義區": 17092.43,
            "內湖區": 21278.14,
            "北投區": 19111.43,
            "南港區": 9827.29,
            "士林區": 20058.71,
            "大同區": 9489.57,
            "大安區": 17518.86,
            "文山區": 20461.86,
            "松山區": 13412.29,
            "萬華區": 14800.86
        },
        "台南市": {
            "七股區": 1037,
            "下營區": 1224.43,
            "中西區": 4916,
            "仁德區": 6685,
            "佳里區": 3686.86,
            "六甲區": 1398.86,
            "北區": 9717.29,
            "北門區": 340.43,
            "南化區": 291.71,
            "南區": 9144.57,
            "善化區": 4310.29,
            "大內區": 407.29,
            "學甲區": 1280.57,
            "安南區": 15332.71,
            "安定區": 2150.86,
            "安平區": 4964.86,
            "官田區": 1405.29,
            "將軍區": 788.71,
            "山上區": 544,
            "左鎮區": 187.57,
            "後壁區": 1197.29,
            "新化區": 3128.43,
            "新市區": 3589,
            "新營區": 5309.43,
            "東區": 12815.43,
            "東山區": 845.43,
            "柳營區": 1436.57,
            "楠西區": 338.57,
            "歸仁區": 5293.86,
            "永康區": 21178.86,
            "玉井區": 709.71,
            "白河區": 1287.57,
            "西港區": 1559,
            "關廟區": 2506.29,
            "鹽水區": 1461.86,
            "麻豆區": 2826.57,
            "龍崎區": 107
        },
        "台東縣": {
            "卑南鄉": 1231.71,
            "台東市": 9580,
            "大武鄉": 290.29,
            "太麻里鄉": 691.57,
            "延平鄉": 311.14,
            "成功鎮": 816.71,
            "東河鄉": 437.71,
            "池上鄉": 406.14,
            "海端鄉": 379,
            "綠島鄉": 221,
            "蘭嶼鄉": 393.71,
            "達仁鄉": 213.86,
            "金峰鄉": 294.14,
            "長濱鄉": 316.29,
            "關山鎮": 516.86,
            "鹿野鄉": 462.29
        },
        "嘉義市": {
            "東區": 8161,
            "西區": 10193.14
        },
        "嘉義縣": {
            "中埔鄉": 2859.86,
            "六腳鄉": 1010.29,
            "大埔鄉": 82.71,
            "大林鎮": 2003,
            "太保市": 2680.57,
            "布袋鎮": 1004.86,
            "新港鄉": 1674.14,
            "朴子市": 2550.14,
            "東石鄉": 768.57,
            "梅山鄉": 793.86,
            "民雄鄉": 5525.14,
            "水上鄉": 3418.71,
            "溪口鄉": 707.29,
            "番路鄉": 506.86,
            "竹崎鄉": 1736.71,
            "義竹鄉": 572,
            "阿里山鄉": 335.43,
            "鹿草鄉": 742.14
        },
        "基隆市": {
            "七堵區": 5348.86,
            "中山區": 4267.29,
            "中正區": 5199,
            "仁愛區": 3556.14,
            "信義區": 5342.57,
            "其他": 0.29,
            "安樂區": 8478.57,
            "暖暖區": 3811.86
        },
        "宜蘭縣": {
            "三星鄉": 1703.43,
            "五結鄉": 3558.29,
            "冬山鄉": 4971.43,
            "南澳鄉": 748,
            "員山鄉": 2689.57,
            "壯圍鄉": 1880.43,
            "大同鄉": 584.43,
            "宜蘭市": 8189.71,
            "礁溪鄉": 3017.29,
            "羅東鎮": 5661,
            "蘇澳鎮": 3350.14,
            "頭城鎮": 2052.43
        },
        "屏東縣": {
            "三地門鄉": 593.86,
            "九如鄉": 1467.86,
            "佳冬鄉": 885,
            "來義鄉": 716,
            "內埔鄉": 4094,
            "南州鄉": 586.71,
            "屏東市": 14536.43,
            "崁頂鄉": 686.57,
            "恆春鎮": 2157.71,
            "新園鄉": 2388.71,
            "新埤鄉": 541.71,
            "春日鄉": 465.14,
            "東港鎮": 3511.43,
            "枋寮鄉": 1467.43,
            "枋山鄉": 217.71,
            "林邊鄉": 876.57,
            "泰武鄉": 601.86,
            "滿州鄉": 314.57,
            "潮州鎮": 4036.29,
            "牡丹鄉": 362.14,
            "獅子鄉": 363.14,
            "琉球鄉": 568.14,
            "瑪家鄉": 684.14,
            "竹田鄉": 1362.29,
            "萬丹鄉": 3734.43,
            "萬巒鄉": 1174.14,
            "車城鄉": 466.71,
            "里港鄉": 1553.43,
            "長治鄉": 2398.71,
            "霧台鄉": 141.57,
            "高樹鄉": 1062.86,
            "鹽埔鄉": 1607.86,
            "麟洛鄉": 732
        },
        "彰化縣": {
            "二林鎮": 3336.43,
            "二水鄉": 807,
            "伸港鄉": 2997,
            "北斗鎮": 2376,
            "和美鎮": 7849.57,
            "員林市": 8926.43,
            "埔心鄉": 2579.86,
            "埔鹽鄉": 2043.14,
            "埤頭鄉": 1830.14,
            "大城鄉": 759.71,
            "大村鄉": 3137.71,
            "彰化市": 18077.57,
            "永靖鄉": 2265.43,
            "溪州鄉": 1629.43,
            "溪湖鎮": 3617.57,
            "田中鎮": 2745.43,
            "田尾鄉": 1528,
            "社頭鄉": 2851.57,
            "福興鄉": 3507.71,
            "秀水鄉": 2919.43,
            "竹塘鄉": 702.71,
            "線西鄉": 1292.57,
            "芬園鄉": 1543.71,
            "花壇鄉": 3720.57,
            "芳苑鄉": 1941.14,
            "鹿港鎮": 7570.43
        },
        "新北市": {
            "三峽區": 10618.57,
            "三芝區": 1419.57,
            "三重區": 42490,
            "中和區": 44430.29,
            "五股區": 9709.29,
            "八里區": 3733.14,
            "土城區": 24354.57,
            "坪林區": 215.57,
            "平溪區": 161.43,
            "新店區": 29878.71,
            "新莊區": 43259.29,
            "板橋區": 56246.57,
            "林口區": 11420.29,
            "樹林區": 16992,
            "永和區": 20930.71,
            "汐止區": 23987.86,
            "泰山區": 8007.29,
            "淡水區": 17930,
            "深坑區": 2649.29,
            "烏來區": 342.29,
            "瑞芳區": 2893.14,
            "石碇區": 342.57,
            "石門區": 315.43,
            "萬里區": 1073.29,
            "蘆洲區": 20523.29,
            "貢寮區": 367,
            "金山區": 1275.57,
            "雙溪區": 305,
            "鶯歌區": 8494.57
        },
        "新竹市": {
            "北區": 12791.57,
            "東區": 20523,
            "香山區": 7360
        },
        "新竹縣": {
            "五峰鄉": 272.14,
            "北埔鄉": 501.43,
            "寶山鄉": 1255,
            "尖石鄉": 642.71,
            "峨眉鄉": 239.29,
            "新埔鎮": 2583.14,
            "新豐鄉": 5358.29,
            "橫山鄉": 821.43,
            "湖口鄉": 8679,
            "竹北市": 19133.43,
            "竹東鎮": 9082.14,
            "芎林鄉": 1602.71,
            "關西鎮": 2003.29
        },
        "桃園市": {
            "中壢區": 39851.14,
            "八德區": 19688.86,
            "大園區": 7767,
            "大溪區": 8451.57,
            "平鎮區": 20769.71,
            "復興區": 809,
            "新屋區": 3966.57,
            "桃園區": 42765.86,
            "楊梅區": 16002.86,
            "蘆竹區": 16780.86,
            "觀音區": 6605.57,
            "龍潭區": 10845.57,
            "龜山區": 19217.57
        },
        "澎湖縣": {
            "七美鄉": 73.71,
            "望安鄉": 68.86,
            "湖西鄉": 869.86,
            "白沙鄉": 327.29,
            "西嶼鄉": 308,
            "馬公市": 3994.86
        },
        "花蓮縣": {
            "光復鄉": 815.86,
            "卓溪鄉": 501.29,
            "吉安鄉": 8770.57,
            "壽豐鄉": 1673.29,
            "富里鄉": 566.86,
            "新城鄉": 2373.86,
            "玉里鎮": 2093.71,
            "瑞穗鄉": 645.57,
            "秀林鄉": 1813.71,
            "花蓮市": 9111,
            "萬榮鄉": 554.86,
            "豐濱鄉": 222.86,
            "鳳林鎮": 686.43
        },
        "苗栗縣": {
            "三灣鄉": 374.86,
            "三義鄉": 1039.57,
            "公館鄉": 2257.57,
            "卓蘭鎮": 737.43,
            "南庄鄉": 544.71,
            "大湖鄉": 659.86,
            "後龍鎮": 2455,
            "泰安鄉": 440.71,
            "獅潭鄉": 149.14,
            "竹南鎮": 8464.43,
            "苑裡鎮": 3351,
            "苗栗市": 7024,
            "西湖鄉": 303.86,
            "通霄鎮": 2000.86,
            "造橋鄉": 1164.29,
            "銅鑼鄉": 1043.14,
            "頭份市": 9381.29,
            "頭屋鄉": 708.57
        },
        "連江縣": {
            "北竿鄉": 128,
            "南竿鄉": 494.43,
            "東引鄉": 137,
            "莒光鄉": 59.86
        },
        "金門縣": {
            "烈嶼鄉": 242.86,
            "烏坵鄉": 6,
            "金城鎮": 1360.43,
            "金寧鄉": 1336.29,
            "金沙鎮": 608,
            "金湖鎮": 1240.29
        },
        "雲林縣": {
            "二崙鄉": 1148.43,
            "元長鄉": 1121.43,
            "北港鎮": 2157.43,
            "口湖鄉": 908.43,
            "古坑鄉": 1613.86,
            "台西鄉": 955.86,
            "四湖鄉": 759,
            "土庫鎮": 1570,
            "大埤鄉": 978.86,
            "崙背鄉": 1237,
            "斗六市": 8612.57,
            "斗南鎮": 2905.43,
            "東勢鄉": 594.86,
            "林內鄉": 962.71,
            "水林鄉": 841.71,
            "莿桐鄉": 1720.43,
            "虎尾鎮": 5729.29,
            "褒忠鄉": 666.14,
            "西螺鎮": 2836.71,
            "麥寮鄉": 2185.29
        },
        "高雄市": {
            "三民區": 25853.71,
            "仁武區": 8418.29,
            "內門區": 643.29,
            "六龜區": 537.71,
            "前金區": 2767.57,
            "前鎮區": 14772.29,
            "大寮區": 10140.14,
            "大樹區": 2977.86,
            "大社區": 2999.57,
            "小港區": 12963.29,
            "岡山區": 7988.71,
            "左營區": 15304.29,
            "彌陀區": 1330.43,
            "新興區": 3560.43,
            "旗山區": 2058.57,
            "旗津區": 1894.14,
            "杉林區": 547.57,
            "林園區": 5160.86,
            "桃源區": 320.43,
            "梓官區": 2817,
            "楠梓區": 16843.57,
            "橋頭區": 3115.29,
            "永安區": 787.57,
            "湖內區": 2288,
            "燕巢區": 2971.86,
            "田寮區": 306.71,
            "甲仙區": 177.86,
            "美濃區": 1807.29,
            "苓雅區": 12156.57,
            "茂林區": 158.71,
            "茄萣區": 2044.57,
            "路竹區": 3962.86,
            "那瑪夏區": 222.57,
            "阿蓮區": 1921.43,
            "鳥松區": 3341.14,
            "鳳山區": 29573.29,
            "鹽埕區": 1606,
            "鼓山區": 10602.14
        }
    }
}