{
    "city": "台中市",
    "area": "新社區",
    "days": {
        "20230116": 14,
        "20230117": 19,
        "20230118": 8,
        "20230119": 9,
        "20230120": 17,
        "20230121": 6,
        "20230122": 7,
        "20230123": 8,
        "20230124": 7,
        "20230125": 9,
        "20230126": 12,
        "20230127": 17,
        "20230128": 29,
        "20230129": 11,
        "20230130": 14,
        "20230131": 21,
        "20230201": 15,
        "20230202": 20,
        "20230203": 9,
        "20230204": 13,
        "20230205": 9,
        "20230206": 24,
        "20230207": 5,
        "20230208": 16,
        "20230209": 13,
        "20230210": 9,
        "20230211": 10,
        "20230212": 3,
        "20230213": 17,
        "20230214": 6,
        "20230215": 12,
        "20230216": 9,
        "20230217": 9,
        "20230218": 12,
        "20230219": 4,
        "20230220": 11,
        "20230221": 12,
        "20230222": 9,
        "20230223": 8,
        "20230224": 10,
        "20230225": 10,
        "20230226": 3,
        "20230227": 12,
        "20230228": 8,
        "20230301": 8,
        "20230302": 7,
        "20230303": 10,
        "20230304": 7,
        "20230305": 2,
        "20230306": 16,
        "20230307": 6,
        "20230308": 11,
        "20230309": 9,
        "20230310": 7,
        "20230311": 6,
        "20230312": 7,
        "20230313": 6,
        "20230314": 6,
        "20230315": 6,
        "20230316": 6
    },
    "gender": {
        "m": 293,
        "f": 333
    },
    "age": {
        "0": 3,
        "1": 8,
        "2": 8,
        "3": 6,
        "4": 4,
        "5-9": 26,
        "10-14": 18,
        "15-19": 51,
        "20-24": 66,
        "25-29": 48,
        "30-34": 46,
        "35-39": 48,
        "40-44": 47,
        "45-49": 40,
        "50-54": 37,
        "55-59": 44,
        "60-64": 30,
        "65-69": 30,
        "70+": 66
    }
}