{
    "city": "屏東縣",
    "area": "萬巒鄉",
    "days": {
        "20230124": 4,
        "20230125": 5,
        "20230126": 12,
        "20230127": 10,
        "20230128": 14,
        "20230129": 8,
        "20230130": 13,
        "20230131": 11,
        "20230201": 14,
        "20230202": 9,
        "20230203": 12,
        "20230204": 10,
        "20230205": 3,
        "20230206": 10,
        "20230207": 8,
        "20230208": 11,
        "20230209": 5,
        "20230210": 4,
        "20230211": 6,
        "20230212": 4,
        "20230213": 7,
        "20230214": 11,
        "20230215": 3,
        "20230216": 8,
        "20230217": 7,
        "20230218": 5,
        "20230219": 7,
        "20230220": 9,
        "20230221": 5,
        "20230222": 4,
        "20230223": 7,
        "20230224": 5,
        "20230225": 7,
        "20230226": 3,
        "20230227": 4,
        "20230228": 9,
        "20230301": 5,
        "20230302": 5,
        "20230303": 4,
        "20230304": 6,
        "20230305": 4,
        "20230306": 4,
        "20230307": 4,
        "20230308": 4,
        "20230309": 3,
        "20230310": 4,
        "20230311": 4,
        "20230312": 6,
        "20230313": 5,
        "20230314": 5,
        "20230315": 4,
        "20230316": 2,
        "20230317": 3,
        "20230318": 1,
        "20230319": 1,
        "20230320": 0,
        "20230321": 0,
        "20230322": 0,
        "20230323": 0
    },
    "gender": {
        "m": 155,
        "f": 193
    },
    "age": {
        "0": 5,
        "1": 6,
        "2": 0,
        "3": 3,
        "4": 4,
        "5-9": 8,
        "10-14": 9,
        "15-19": 17,
        "20-24": 32,
        "25-29": 38,
        "30-34": 26,
        "35-39": 18,
        "40-44": 26,
        "45-49": 19,
        "50-54": 30,
        "55-59": 28,
        "60-64": 16,
        "65-69": 27,
        "70+": 36
    }
}