{
    "city": "屏東縣",
    "area": "佳冬鄉",
    "days": {
        "20220725": 15,
        "20220726": 6,
        "20220727": 6,
        "20220728": 11,
        "20220729": 7,
        "20220730": 7,
        "20220731": 8,
        "20220801": 17,
        "20220802": 12,
        "20220803": 8,
        "20220804": 10,
        "20220805": 11,
        "20220806": 9,
        "20220807": 2,
        "20220808": 12,
        "20220809": 3,
        "20220810": 8,
        "20220811": 11,
        "20220812": 6,
        "20220813": 5,
        "20220814": 3,
        "20220815": 7,
        "20220816": 6,
        "20220817": 5,
        "20220818": 7,
        "20220819": 9,
        "20220820": 9,
        "20220821": 7,
        "20220822": 5,
        "20220823": 4,
        "20220824": 12,
        "20220825": 9,
        "20220826": 6,
        "20220827": 5,
        "20220828": 7,
        "20220829": 6,
        "20220830": 6,
        "20220831": 2,
        "20220901": 15,
        "20220902": 16,
        "20220903": 12,
        "20220904": 12,
        "20220905": 15,
        "20220906": 18,
        "20220907": 15,
        "20220908": 11,
        "20220909": 20,
        "20220910": 12,
        "20220911": 8,
        "20220912": 38,
        "20220913": 14,
        "20220914": 23,
        "20220915": 16,
        "20220916": 17,
        "20220917": 12,
        "20220918": 9,
        "20220919": 30,
        "20220920": 26,
        "20220921": 31,
        "20220922": 0
    },
    "gender": {
        "m": 302,
        "f": 357
    },
    "age": {
        "0": 4,
        "1": 8,
        "2": 7,
        "3": 5,
        "4": 8,
        "5-9": 57,
        "10-14": 47,
        "15-19": 46,
        "20-24": 37,
        "25-29": 43,
        "30-34": 49,
        "35-39": 48,
        "40-44": 47,
        "45-49": 33,
        "50-54": 38,
        "55-59": 39,
        "60-64": 41,
        "65-69": 40,
        "70+": 62
    }
}