{
    "city": "新北市",
    "area": "林口區",
    "days": {
        "20220228": 0,
        "20220301": 0,
        "20220302": 0,
        "20220303": 0,
        "20220304": 0,
        "20220305": 0,
        "20220306": 0,
        "20220307": 0,
        "20220308": 0,
        "20220309": 0,
        "20220310": 0,
        "20220311": 0,
        "20220312": 0,
        "20220313": 0,
        "20220314": 0,
        "20220315": 0,
        "20220316": 0,
        "20220317": 0,
        "20220318": 0,
        "20220319": 0,
        "20220320": 0,
        "20220321": 0,
        "20220322": 0,
        "20220323": 0,
        "20220324": 0,
        "20220325": 0,
        "20220326": 0,
        "20220327": 0,
        "20220328": 0,
        "20220329": 0,
        "20220330": 3,
        "20220331": 0,
        "20220401": 0,
        "20220402": 0,
        "20220403": 1,
        "20220404": 2,
        "20220405": 2,
        "20220406": 2,
        "20220407": 0,
        "20220408": 4,
        "20220409": 2,
        "20220410": 3,
        "20220411": 4,
        "20220412": 5,
        "20220413": 5,
        "20220414": 1,
        "20220415": 10,
        "20220416": 14,
        "20220417": 10,
        "20220418": 13,
        "20220419": 17,
        "20220420": 16,
        "20220421": 22,
        "20220422": 28,
        "20220423": 51,
        "20220424": 40,
        "20220425": 82,
        "20220426": 91,
        "20220427": 66,
        "20220428": 12
    },
    "gender": {
        "m": 260,
        "f": 246
    },
    "age": {
        "0": 5,
        "1": 5,
        "2": 3,
        "3": 2,
        "4": 4,
        "5-9": 61,
        "10-14": 19,
        "15-19": 39,
        "20-24": 59,
        "25-29": 63,
        "30-34": 45,
        "35-39": 45,
        "40-44": 64,
        "45-49": 29,
        "50-54": 25,
        "55-59": 17,
        "60-64": 10,
        "65-69": 5,
        "70+": 6
    }
}