{
    "city": "新北市",
    "area": "石碇區",
    "days": {
        "20220611": 9,
        "20220612": 5,
        "20220613": 8,
        "20220614": 2,
        "20220615": 7,
        "20220616": 1,
        "20220617": 7,
        "20220618": 8,
        "20220619": 2,
        "20220620": 6,
        "20220621": 3,
        "20220622": 3,
        "20220623": 1,
        "20220624": 3,
        "20220625": 9,
        "20220626": 2,
        "20220627": 5,
        "20220628": 6,
        "20220629": 9,
        "20220630": 3,
        "20220701": 3,
        "20220702": 3,
        "20220703": 1,
        "20220704": 7,
        "20220705": 8,
        "20220706": 4,
        "20220707": 8,
        "20220708": 7,
        "20220709": 17,
        "20220710": 1,
        "20220711": 13,
        "20220712": 3,
        "20220713": 4,
        "20220714": 3,
        "20220715": 4,
        "20220716": 6,
        "20220717": 1,
        "20220718": 3,
        "20220719": 2,
        "20220720": 8,
        "20220721": 7,
        "20220722": 2,
        "20220723": 0,
        "20220724": 6,
        "20220725": 2,
        "20220726": 3,
        "20220727": 2,
        "20220728": 6,
        "20220729": 9,
        "20220730": 3,
        "20220731": 4,
        "20220801": 5,
        "20220802": 2,
        "20220803": 1,
        "20220804": 5,
        "20220805": 1,
        "20220806": 2,
        "20220807": 2,
        "20220808": 5
    },
    "gender": {
        "m": 121,
        "f": 151
    },
    "age": {
        "0": 4,
        "1": 0,
        "2": 2,
        "3": 2,
        "4": 2,
        "5-9": 14,
        "10-14": 9,
        "15-19": 11,
        "20-24": 21,
        "25-29": 31,
        "30-34": 19,
        "35-39": 13,
        "40-44": 26,
        "45-49": 15,
        "50-54": 23,
        "55-59": 14,
        "60-64": 24,
        "65-69": 14,
        "70+": 28
    }
}