{
    "city": "花蓮縣",
    "area": "光復鄉",
    "days": {
        "20220923": 8,
        "20220924": 7,
        "20220925": 6,
        "20220926": 6,
        "20220927": 20,
        "20220928": 9,
        "20220929": 5,
        "20220930": 7,
        "20221001": 4,
        "20221002": 7,
        "20221003": 8,
        "20221004": 16,
        "20221005": 10,
        "20221006": 4,
        "20221007": 12,
        "20221008": 18,
        "20221009": 5,
        "20221010": 12,
        "20221011": 19,
        "20221012": 14,
        "20221013": 15,
        "20221014": 12,
        "20221015": 15,
        "20221016": 2,
        "20221017": 20,
        "20221018": 9,
        "20221019": 11,
        "20221020": 18,
        "20221021": 9,
        "20221022": 10,
        "20221023": 0,
        "20221024": 6,
        "20221025": 7,
        "20221026": 6,
        "20221027": 8,
        "20221028": 9,
        "20221029": 5,
        "20221030": 1,
        "20221031": 9,
        "20221101": 7,
        "20221102": 4,
        "20221103": 11,
        "20221104": 13,
        "20221105": 9,
        "20221106": 3,
        "20221107": 16,
        "20221108": 6,
        "20221109": 6,
        "20221110": 4,
        "20221111": 3,
        "20221112": 4,
        "20221113": 1,
        "20221114": 5,
        "20221115": 1,
        "20221116": 3,
        "20221117": 2,
        "20221118": 3,
        "20221119": 5,
        "20221120": 1,
        "20221121": 5
    },
    "gender": {
        "m": 227,
        "f": 254
    },
    "age": {
        "0": 3,
        "1": 4,
        "2": 3,
        "3": 1,
        "4": 3,
        "5-9": 21,
        "10-14": 27,
        "15-19": 24,
        "20-24": 6,
        "25-29": 31,
        "30-34": 25,
        "35-39": 19,
        "40-44": 21,
        "45-49": 17,
        "50-54": 23,
        "55-59": 41,
        "60-64": 54,
        "65-69": 53,
        "70+": 105
    }
}