{
    "meta": {
        "day": "20220123",
        "total": 267,
        "modified": "2022-01-23 15:15:04"
    },
    "data": {
        "台中市": {
            "豐原區": 1
        },
        "台北市": {
            "中山區": 1,
            "內湖區": 1,
            "北投區": 4,
            "士林區": 2,
            "大同區": 3,
            "萬華區": 1
        },
        "基隆市": {
            "中正區": 1,
            "安樂區": 1
        },
        "新北市": {
            "三重區": 1,
            "土城區": 2,
            "新店區": 1,
            "板橋區": 5,
            "永和區": 1,
            "蘆洲區": 1,
            "鶯歌區": 1
        },
        "新竹市": {
            "東區": 4,
            "香山區": 1
        },
        "新竹縣": {
            "新豐鄉": 2
        },
        "桃園市": {
            "中壢區": 71,
            "八德區": 10,
            "大園區": 66,
            "大溪區": 6,
            "平鎮區": 15,
            "新屋區": 1,
            "桃園區": 10,
            "楊梅區": 4,
            "蘆竹區": 1,
            "觀音區": 5,
            "龍潭區": 2,
            "龜山區": 1
        },
        "高雄市": {
            "三民區": 1,
            "前金區": 2,
            "前鎮區": 9,
            "小港區": 5,
            "岡山區": 1,
            "左營區": 2,
            "新興區": 4,
            "旗津區": 2,
            "楠梓區": 1,
            "苓雅區": 5,
            "鳳山區": 7,
            "鼓山區": 2
        }
    },
    "rate": {
        "台中市": {
            "豐原區": 1
        },
        "台北市": {
            "中山區": 1,
            "內湖區": 1,
            "北投區": 1,
            "士林區": 1,
            "大同區": 1,
            "萬華區": 1
        },
        "基隆市": {
            "中正區": 1,
            "安樂區": 1
        },
        "新北市": {
            "三重區": 1,
            "土城區": 1,
            "新店區": 1,
            "板橋區": 1,
            "永和區": 1,
            "蘆洲區": 1,
            "鶯歌區": 1
        },
        "新竹市": {
            "東區": 1,
            "香山區": 1
        },
        "新竹縣": {
            "新豐鄉": 1
        },
        "桃園市": {
            "中壢區": 1,
            "八德區": 1,
            "大園區": 1,
            "大溪區": 1,
            "平鎮區": 1,
            "新屋區": 1,
            "桃園區": 1,
            "楊梅區": 1,
            "蘆竹區": 1,
            "觀音區": 1,
            "龍潭區": 1,
            "龜山區": 1
        },
        "高雄市": {
            "三民區": 1,
            "前金區": 1,
            "前鎮區": 1,
            "小港區": 1,
            "岡山區": 1,
            "左營區": 1,
            "新興區": 1,
            "旗津區": 1,
            "楠梓區": 1,
            "苓雅區": 1,
            "鳳山區": 1,
            "鼓山區": 1
        }
    },
    "increase": {
        "台中市": {
            "豐原區": 1
        },
        "台北市": {
            "中山區": 1,
            "內湖區": 1,
            "北投區": 4,
            "士林區": 2,
            "大同區": 3,
            "萬華區": 1
        },
        "基隆市": {
            "中正區": 1,
            "安樂區": 1
        },
        "新北市": {
            "三重區": 1,
            "土城區": 2,
            "新店區": 1,
            "板橋區": 5,
            "永和區": 1,
            "蘆洲區": 1,
            "鶯歌區": 1
        },
        "新竹市": {
            "東區": 4,
            "香山區": 1
        },
        "新竹縣": {
            "新豐鄉": 2
        },
        "桃園市": {
            "中壢區": 71,
            "八德區": 10,
            "大園區": 66,
            "大溪區": 6,
            "平鎮區": 15,
            "新屋區": 1,
            "桃園區": 10,
            "楊梅區": 4,
            "蘆竹區": 1,
            "觀音區": 5,
            "龍潭區": 2,
            "龜山區": 1
        },
        "高雄市": {
            "三民區": 1,
            "前金區": 2,
            "前鎮區": 9,
            "小港區": 5,
            "岡山區": 1,
            "左營區": 2,
            "新興區": 4,
            "旗津區": 2,
            "楠梓區": 1,
            "苓雅區": 5,
            "鳳山區": 7,
            "鼓山區": 2
        }
    },
    "avg7": {
        "台中市": {
            "豐原區": 0.14
        },
        "台北市": {
            "中山區": 0.14,
            "內湖區": 0.29,
            "北投區": 0.71,
            "士林區": 0.29,
            "大同區": 0.57,
            "萬華區": 0.29
        },
        "基隆市": {
            "中正區": 0.29,
            "安樂區": 0.14
        },
        "新北市": {
            "三重區": 0.14,
            "土城區": 0.29,
            "新店區": 0.14,
            "板橋區": 1.14,
            "永和區": 0.14,
            "蘆洲區": 0.14,
            "鶯歌區": 0.14
        },
        "新竹市": {
            "東區": 1.14,
            "香山區": 0.29
        },
        "新竹縣": {
            "新豐鄉": 0.29
        },
        "桃園市": {
            "中壢區": 13,
            "八德區": 2.14,
            "大園區": 15.71,
            "大溪區": 1.14,
            "平鎮區": 3,
            "新屋區": 0.29,
            "桃園區": 1.71,
            "楊梅區": 0.71,
            "蘆竹區": 0.14,
            "觀音區": 1.14,
            "龍潭區": 0.43,
            "龜山區": 0.14
        },
        "高雄市": {
            "三民區": 0.29,
            "前金區": 0.29,
            "前鎮區": 2.43,
            "小港區": 1.14,
            "岡山區": 0.14,
            "左營區": 0.29,
            "新興區": 0.57,
            "旗津區": 0.57,
            "楠梓區": 0.14,
            "苓雅區": 1,
            "鳳山區": 1.71,
            "鼓山區": 0.29
        }
    }
}