{
    "meta": {
        "day": "20220530",
        "total": 2003049,
        "modified": "2022-06-02 01:46:14"
    },
    "data": {
        "南投縣": {
            "中寮鄉": 312,
            "仁愛鄉": 989,
            "信義鄉": 875,
            "南投市": 4707,
            "名間鄉": 1300,
            "國姓鄉": 475,
            "埔里鎮": 2963,
            "水里鄉": 393,
            "竹山鎮": 2188,
            "草屯鎮": 3588,
            "集集鎮": 238,
            "魚池鄉": 282,
            "鹿谷鄉": 446
        },
        "台中市": {
            "中區": 1276,
            "北區": 10222,
            "北屯區": 16483,
            "南區": 7865,
            "南屯區": 9974,
            "后里區": 2530,
            "和平區": 437,
            "外埔區": 1357,
            "大安區": 856,
            "大甲區": 3792,
            "大肚區": 3199,
            "大里區": 13005,
            "大雅區": 6095,
            "太平區": 12261,
            "新社區": 733,
            "東勢區": 1854,
            "東區": 5017,
            "梧棲區": 5261,
            "沙鹿區": 7250,
            "清水區": 5932,
            "潭子區": 6086,
            "烏日區": 5053,
            "石岡區": 529,
            "神岡區": 3836,
            "西區": 6577,
            "西屯區": 15907,
            "豐原區": 8113,
            "霧峰區": 4126,
            "龍井區": 5021
        },
        "台北市": {
            "中山區": 23141,
            "中正區": 12019,
            "信義區": 22853,
            "內湖區": 25997,
            "北投區": 27656,
            "南港區": 13486,
            "士林區": 27102,
            "大同區": 13978,
            "大安區": 21942,
            "文山區": 27588,
            "松山區": 16786,
            "萬華區": 27018
        },
        "台南市": {
            "七股區": 730,
            "下營區": 700,
            "中西區": 3703,
            "仁德區": 5104,
            "佳里區": 2377,
            "六甲區": 825,
            "北區": 7395,
            "北門區": 208,
            "南化區": 143,
            "南區": 7388,
            "善化區": 3020,
            "大內區": 291,
            "學甲區": 814,
            "安南區": 11531,
            "安定區": 1576,
            "安平區": 3680,
            "官田區": 855,
            "將軍區": 535,
            "山上區": 486,
            "左鎮區": 206,
            "後壁區": 645,
            "新化區": 2556,
            "新市區": 2644,
            "新營區": 3457,
            "東區": 9067,
            "東山區": 484,
            "柳營區": 1115,
            "楠西區": 165,
            "歸仁區": 3936,
            "永康區": 17919,
            "玉井區": 379,
            "白河區": 566,
            "西港區": 1012,
            "關廟區": 2102,
            "鹽水區": 802,
            "麻豆區": 1940,
            "龍崎區": 70
        },
        "台東縣": {
            "卑南鄉": 915,
            "台東市": 7641,
            "大武鄉": 187,
            "太麻里鄉": 557,
            "延平鄉": 258,
            "成功鎮": 734,
            "東河鄉": 387,
            "池上鄉": 277,
            "海端鄉": 432,
            "綠島鄉": 257,
            "蘭嶼鄉": 442,
            "達仁鄉": 90,
            "金峰鄉": 270,
            "長濱鄉": 410,
            "關山鎮": 487,
            "鹿野鄉": 322
        },
        "嘉義市": {
            "東區": 4374,
            "西區": 5689
        },
        "嘉義縣": {
            "中埔鄉": 1445,
            "六腳鄉": 533,
            "大埔鄉": 43,
            "大林鎮": 1264,
            "太保市": 1416,
            "布袋鎮": 571,
            "新港鄉": 781,
            "朴子市": 1335,
            "東石鄉": 311,
            "梅山鄉": 449,
            "民雄鄉": 2923,
            "水上鄉": 2309,
            "溪口鄉": 388,
            "番路鄉": 254,
            "竹崎鄉": 783,
            "義竹鄉": 308,
            "阿里山鄉": 171,
            "鹿草鄉": 480
        },
        "基隆市": {
            "七堵區": 8154,
            "中山區": 6691,
            "中正區": 8445,
            "仁愛區": 6352,
            "信義區": 8425,
            "其他": 1,
            "安樂區": 12320,
            "暖暖區": 5766
        },
        "宜蘭縣": {
            "三星鄉": 1886,
            "五結鄉": 3602,
            "冬山鄉": 5050,
            "南澳鄉": 1441,
            "員山鄉": 2957,
            "壯圍鄉": 1945,
            "大同鄉": 995,
            "宜蘭市": 8548,
            "礁溪鄉": 3641,
            "羅東鎮": 6356,
            "蘇澳鎮": 4415,
            "頭城鎮": 2384
        },
        "屏東縣": {
            "三地門鄉": 584,
            "九如鄉": 1074,
            "佳冬鄉": 587,
            "來義鄉": 665,
            "內埔鄉": 3021,
            "南州鄉": 401,
            "屏東市": 12388,
            "崁頂鄉": 407,
            "恆春鎮": 1594,
            "新園鄉": 2345,
            "新埤鄉": 388,
            "春日鄉": 401,
            "東港鎮": 3572,
            "枋寮鄉": 957,
            "枋山鄉": 158,
            "林邊鄉": 619,
            "泰武鄉": 568,
            "滿州鄉": 197,
            "潮州鎮": 2957,
            "牡丹鄉": 250,
            "獅子鄉": 317,
            "琉球鄉": 262,
            "瑪家鄉": 648,
            "竹田鄉": 622,
            "萬丹鄉": 3091,
            "萬巒鄉": 758,
            "車城鄉": 310,
            "里港鄉": 1184,
            "長治鄉": 1867,
            "霧台鄉": 111,
            "高樹鄉": 624,
            "鹽埔鄉": 1250,
            "麟洛鄉": 612
        },
        "彰化縣": {
            "二林鎮": 2314,
            "二水鄉": 393,
            "伸港鄉": 1692,
            "北斗鎮": 1391,
            "和美鎮": 4578,
            "員林市": 5675,
            "埔心鄉": 1512,
            "埔鹽鄉": 1011,
            "埤頭鄉": 1076,
            "大城鄉": 519,
            "大村鄉": 2025,
            "彰化市": 11252,
            "永靖鄉": 1308,
            "溪州鄉": 938,
            "溪湖鎮": 1755,
            "田中鎮": 1489,
            "田尾鄉": 792,
            "社頭鄉": 1519,
            "福興鄉": 1886,
            "秀水鄉": 1524,
            "竹塘鄉": 415,
            "線西鄉": 780,
            "芬園鄉": 929,
            "花壇鄉": 2337,
            "芳苑鄉": 1233,
            "鹿港鎮": 4951
        },
        "新北市": {
            "三峽區": 14228,
            "三芝區": 1530,
            "三重區": 68898,
            "中和區": 68541,
            "五股區": 13905,
            "八里區": 4754,
            "土城區": 36414,
            "坪林區": 218,
            "平溪區": 211,
            "新店區": 41610,
            "新莊區": 67406,
            "板橋區": 86308,
            "林口區": 12909,
            "樹林區": 25529,
            "永和區": 29062,
            "汐止區": 33607,
            "泰山區": 11529,
            "淡水區": 21405,
            "深坑區": 3542,
            "烏來區": 540,
            "瑞芳區": 4744,
            "石碇區": 471,
            "石門區": 386,
            "萬里區": 1582,
            "蘆洲區": 29245,
            "貢寮區": 383,
            "金山區": 1645,
            "雙溪區": 349,
            "鶯歌區": 11899
        },
        "新竹市": {
            "北區": 10445,
            "東區": 17786,
            "香山區": 6245
        },
        "新竹縣": {
            "五峰鄉": 370,
            "北埔鄉": 364,
            "寶山鄉": 1241,
            "尖石鄉": 898,
            "峨眉鄉": 211,
            "新埔鎮": 2139,
            "新豐鄉": 5746,
            "橫山鄉": 701,
            "湖口鄉": 11487,
            "竹北市": 17198,
            "竹東鎮": 8295,
            "芎林鄉": 1290,
            "關西鎮": 1757
        },
        "桃園市": {
            "中壢區": 49148,
            "八德區": 25259,
            "大園區": 9694,
            "大溪區": 11367,
            "平鎮區": 24772,
            "復興區": 1158,
            "新屋區": 5117,
            "桃園區": 58506,
            "楊梅區": 20099,
            "蘆竹區": 20879,
            "觀音區": 8257,
            "龍潭區": 12513,
            "龜山區": 27288
        },
        "澎湖縣": {
            "七美鄉": 47,
            "望安鄉": 12,
            "湖西鄉": 339,
            "白沙鄉": 162,
            "西嶼鄉": 128,
            "馬公市": 2212
        },
        "花蓮縣": {
            "光復鄉": 988,
            "卓溪鄉": 707,
            "吉安鄉": 8152,
            "壽豐鄉": 1497,
            "富里鄉": 738,
            "新城鄉": 2912,
            "玉里鎮": 2449,
            "瑞穗鄉": 790,
            "秀林鄉": 3886,
            "花蓮市": 8239,
            "萬榮鄉": 855,
            "豐濱鄉": 274,
            "鳳林鎮": 687
        },
        "苗栗縣": {
            "三灣鄉": 299,
            "三義鄉": 584,
            "公館鄉": 1212,
            "卓蘭鎮": 501,
            "南庄鄉": 526,
            "大湖鄉": 382,
            "後龍鎮": 1597,
            "泰安鄉": 365,
            "獅潭鄉": 71,
            "竹南鎮": 7787,
            "苑裡鎮": 2319,
            "苗栗市": 3992,
            "西湖鄉": 155,
            "通霄鎮": 1545,
            "造橋鄉": 1173,
            "銅鑼鄉": 572,
            "頭份市": 7579,
            "頭屋鄉": 391
        },
        "連江縣": {
            "北竿鄉": 90,
            "南竿鄉": 349,
            "東引鄉": 84,
            "莒光鄉": 61
        },
        "金門縣": {
            "烈嶼鄉": 106,
            "烏坵鄉": 2,
            "金城鎮": 699,
            "金寧鄉": 658,
            "金沙鎮": 325,
            "金湖鎮": 577
        },
        "雲林縣": {
            "二崙鄉": 673,
            "元長鄉": 748,
            "北港鎮": 1303,
            "口湖鄉": 566,
            "古坑鄉": 935,
            "台西鄉": 532,
            "四湖鄉": 440,
            "土庫鎮": 895,
            "大埤鄉": 553,
            "崙背鄉": 765,
            "斗六市": 4764,
            "斗南鎮": 1567,
            "東勢鄉": 369,
            "林內鄉": 541,
            "水林鄉": 496,
            "莿桐鄉": 963,
            "虎尾鎮": 3484,
            "褒忠鄉": 413,
            "西螺鎮": 2267,
            "麥寮鄉": 1256
        },
        "高雄市": {
            "三民區": 20287,
            "仁武區": 5726,
            "內門區": 432,
            "六龜區": 332,
            "前金區": 2726,
            "前鎮區": 11456,
            "大寮區": 7322,
            "大樹區": 2225,
            "大社區": 2210,
            "小港區": 12815,
            "岡山區": 6765,
            "左營區": 10175,
            "彌陀區": 1037,
            "新興區": 2772,
            "旗山區": 1143,
            "旗津區": 1528,
            "杉林區": 337,
            "林園區": 3533,
            "桃源區": 244,
            "梓官區": 2392,
            "楠梓區": 12925,
            "橋頭區": 2143,
            "永安區": 567,
            "湖內區": 1907,
            "燕巢區": 3611,
            "田寮區": 240,
            "甲仙區": 104,
            "美濃區": 950,
            "苓雅區": 9772,
            "茂林區": 100,
            "茄萣區": 2008,
            "路竹區": 3721,
            "那瑪夏區": 174,
            "阿蓮區": 1291,
            "鳥松區": 2460,
            "鳳山區": 23268,
            "鹽埕區": 1161,
            "鼓山區": 7160
        }
    },
    "rate": {
        "南投縣": {
            "中寮鄉": 0.1,
            "仁愛鄉": 0.1,
            "信義鄉": 0.1,
            "南投市": 0.1,
            "名間鄉": 0.1,
            "國姓鄉": 0.1,
            "埔里鎮": 0.1,
            "水里鄉": 0.1,
            "竹山鎮": 0.1,
            "草屯鎮": 0.1,
            "集集鎮": 0.1,
            "魚池鄉": 0.1,
            "鹿谷鄉": 0.1
        },
        "台中市": {
            "中區": 0.1,
            "北區": 0.1,
            "北屯區": 0.1,
            "南區": 0.1,
            "南屯區": 0.1,
            "后里區": 0.1,
            "和平區": 0.1,
            "外埔區": 0.1,
            "大安區": 0.1,
            "大甲區": 0.1,
            "大肚區": 0.1,
            "大里區": 0.1,
            "大雅區": 0.1,
            "太平區": 0.1,
            "新社區": 0.1,
            "東勢區": 0.1,
            "東區": 0.1,
            "梧棲區": 0.1,
            "沙鹿區": 0.1,
            "清水區": 0.1,
            "潭子區": 0.1,
            "烏日區": 0.1,
            "石岡區": 0.1,
            "神岡區": 0.1,
            "西區": 0.1,
            "西屯區": 0.1,
            "豐原區": 0.1,
            "霧峰區": 0.1,
            "龍井區": 0.1
        },
        "台北市": {
            "中山區": 0,
            "中正區": 0,
            "信義區": 0,
            "內湖區": 0,
            "北投區": 0,
            "南港區": 0,
            "士林區": 0,
            "大同區": 0,
            "大安區": 0,
            "文山區": 0,
            "松山區": 0,
            "萬華區": 0
        },
        "台南市": {
            "七股區": 0.1,
            "下營區": 0.1,
            "中西區": 0.1,
            "仁德區": 0.1,
            "佳里區": 0.1,
            "六甲區": 0.1,
            "北區": 0.1,
            "北門區": 0.1,
            "南化區": 0.1,
            "南區": 0.1,
            "善化區": 0.1,
            "大內區": 0.1,
            "學甲區": 0.1,
            "安南區": 0.1,
            "安定區": 0.1,
            "安平區": 0.1,
            "官田區": 0.1,
            "將軍區": 0.1,
            "山上區": 0,
            "左鎮區": 0.1,
            "後壁區": 0.1,
            "新化區": 0.1,
            "新市區": 0.1,
            "新營區": 0.1,
            "東區": 0.1,
            "東山區": 0.1,
            "柳營區": 0.1,
            "楠西區": 0.2,
            "歸仁區": 0.1,
            "永康區": 0.1,
            "玉井區": 0.2,
            "白河區": 0.1,
            "西港區": 0.1,
            "關廟區": 0.1,
            "鹽水區": 0.1,
            "麻豆區": 0.1,
            "龍崎區": 0.1
        },
        "台東縣": {
            "卑南鄉": 0.1,
            "台東市": 0.1,
            "大武鄉": 0.1,
            "太麻里鄉": 0.1,
            "延平鄉": 0.1,
            "成功鎮": 0,
            "東河鄉": 0,
            "池上鄉": 0.1,
            "海端鄉": 0,
            "綠島鄉": 0,
            "蘭嶼鄉": 0,
            "達仁鄉": 0.1,
            "金峰鄉": 0,
            "長濱鄉": 0.1,
            "關山鎮": 0.1,
            "鹿野鄉": 0.1
        },
        "嘉義市": {
            "東區": 0.1,
            "西區": 0.1
        },
        "嘉義縣": {
            "中埔鄉": 0.1,
            "六腳鄉": 0.1,
            "大埔鄉": 0.3,
            "大林鎮": 0.1,
            "太保市": 0.1,
            "布袋鎮": 0,
            "新港鄉": 0.1,
            "朴子市": 0.1,
            "東石鄉": 0.1,
            "梅山鄉": 0.1,
            "民雄鄉": 0.1,
            "水上鄉": 0.1,
            "溪口鄉": 0,
            "番路鄉": 0.1,
            "竹崎鄉": 0.1,
            "義竹鄉": 0.1,
            "阿里山鄉": 0.1,
            "鹿草鄉": 0.1
        },
        "基隆市": {
            "七堵區": 0,
            "中山區": 0,
            "中正區": 0,
            "仁愛區": 0,
            "信義區": 0,
            "其他": 0,
            "安樂區": 0,
            "暖暖區": 0
        },
        "宜蘭縣": {
            "三星鄉": 0,
            "五結鄉": 0,
            "冬山鄉": 0,
            "南澳鄉": 0,
            "員山鄉": 0,
            "壯圍鄉": 0,
            "大同鄉": 0,
            "宜蘭市": 0,
            "礁溪鄉": 0,
            "羅東鎮": 0,
            "蘇澳鎮": 0.1,
            "頭城鎮": 0
        },
        "屏東縣": {
            "三地門鄉": 0.1,
            "九如鄉": 0.1,
            "佳冬鄉": 0.1,
            "來義鄉": 0.1,
            "內埔鄉": 0.1,
            "南州鄉": 0.1,
            "屏東市": 0,
            "崁頂鄉": 0.1,
            "恆春鎮": 0.1,
            "新園鄉": 0.1,
            "新埤鄉": 0.1,
            "春日鄉": 0.1,
            "東港鎮": 0.1,
            "枋寮鄉": 0.1,
            "枋山鄉": 0.1,
            "林邊鄉": 0.1,
            "泰武鄉": 0.1,
            "滿州鄉": 0.1,
            "潮州鎮": 0.1,
            "牡丹鄉": 0.1,
            "獅子鄉": 0.1,
            "琉球鄉": 0,
            "瑪家鄉": 0.1,
            "竹田鄉": 0.1,
            "萬丹鄉": 0.1,
            "萬巒鄉": 0.1,
            "車城鄉": 0.1,
            "里港鄉": 0.1,
            "長治鄉": 0.1,
            "霧台鄉": 0.1,
            "高樹鄉": 0.1,
            "鹽埔鄉": 0.1,
            "麟洛鄉": 0.1
        },
        "彰化縣": {
            "二林鎮": 0.1,
            "二水鄉": 0.1,
            "伸港鄉": 0.1,
            "北斗鎮": 0.1,
            "和美鎮": 0.1,
            "員林市": 0.1,
            "埔心鄉": 0.1,
            "埔鹽鄉": 0.1,
            "埤頭鄉": 0.1,
            "大城鄉": 0.2,
            "大村鄉": 0.1,
            "彰化市": 0.1,
            "永靖鄉": 0.1,
            "溪州鄉": 0.1,
            "溪湖鎮": 0.1,
            "田中鎮": 0.1,
            "田尾鄉": 0.1,
            "社頭鄉": 0.1,
            "福興鄉": 0.1,
            "秀水鄉": 0,
            "竹塘鄉": 0.1,
            "線西鄉": 0.1,
            "芬園鄉": 0.1,
            "花壇鄉": 0.1,
            "芳苑鄉": 0.1,
            "鹿港鎮": 0.1
        },
        "新北市": {
            "三峽區": 0,
            "三芝區": 0.1,
            "三重區": 0,
            "中和區": 0,
            "五股區": 0,
            "八里區": 0,
            "土城區": 0,
            "坪林區": 0.1,
            "平溪區": 0,
            "新店區": 0,
            "新莊區": 0,
            "板橋區": 0,
            "林口區": 0,
            "樹林區": 0,
            "永和區": 0,
            "汐止區": 0,
            "泰山區": 0,
            "淡水區": 0,
            "深坑區": 0,
            "烏來區": 0,
            "瑞芳區": 0,
            "石碇區": 0,
            "石門區": 0,
            "萬里區": 0,
            "蘆洲區": 0,
            "貢寮區": 0,
            "金山區": 0,
            "雙溪區": 0.1,
            "鶯歌區": 0
        },
        "新竹市": {
            "北區": 0.1,
            "東區": 0.1,
            "香山區": 0.1
        },
        "新竹縣": {
            "五峰鄉": 0,
            "北埔鄉": 0.1,
            "寶山鄉": 0,
            "尖石鄉": 0,
            "峨眉鄉": 0.1,
            "新埔鎮": 0,
            "新豐鄉": 0,
            "橫山鄉": 0.1,
            "湖口鄉": 0,
            "竹北市": 0,
            "竹東鎮": 0,
            "芎林鄉": 0.1,
            "關西鎮": 0
        },
        "桃園市": {
            "中壢區": 0,
            "八德區": 0,
            "大園區": 0,
            "大溪區": 0.1,
            "平鎮區": 0,
            "復興區": 0.1,
            "新屋區": 0,
            "桃園區": 0,
            "楊梅區": 0,
            "蘆竹區": 0,
            "觀音區": 0,
            "龍潭區": 0,
            "龜山區": 0
        },
        "澎湖縣": {
            "七美鄉": 0.1,
            "望安鄉": 0.3,
            "湖西鄉": 0.1,
            "白沙鄉": 0,
            "西嶼鄉": 0.1,
            "馬公市": 0.1
        },
        "花蓮縣": {
            "光復鄉": 0,
            "卓溪鄉": 0,
            "吉安鄉": 0,
            "壽豐鄉": 0.1,
            "富里鄉": 0,
            "新城鄉": 0,
            "玉里鎮": 0.1,
            "瑞穗鄉": 0,
            "秀林鄉": 0,
            "花蓮市": 0,
            "萬榮鄉": 0,
            "豐濱鄉": 0,
            "鳳林鎮": 0
        },
        "苗栗縣": {
            "三灣鄉": 0.1,
            "三義鄉": 0.1,
            "公館鄉": 0.1,
            "卓蘭鎮": 0.1,
            "南庄鄉": 0.1,
            "大湖鄉": 0,
            "後龍鎮": 0.1,
            "泰安鄉": 0.1,
            "獅潭鄉": 0.1,
            "竹南鎮": 0,
            "苑裡鎮": 0.1,
            "苗栗市": 0.1,
            "西湖鄉": 0,
            "通霄鎮": 0.1,
            "造橋鄉": 0.1,
            "銅鑼鄉": 0.1,
            "頭份市": 0.1,
            "頭屋鄉": 0.1
        },
        "連江縣": {
            "北竿鄉": 0,
            "南竿鄉": 0,
            "東引鄉": 0,
            "莒光鄉": 0
        },
        "金門縣": {
            "烈嶼鄉": 0.1,
            "烏坵鄉": 0,
            "金城鎮": 0.1,
            "金寧鄉": 0,
            "金沙鎮": 0.1,
            "金湖鎮": 0.1
        },
        "雲林縣": {
            "二崙鄉": 0.1,
            "元長鄉": 0.1,
            "北港鎮": 0.1,
            "口湖鄉": 0,
            "古坑鄉": 0.1,
            "台西鄉": 0,
            "四湖鄉": 0.1,
            "土庫鎮": 0.1,
            "大埤鄉": 0.1,
            "崙背鄉": 0.1,
            "斗六市": 0.1,
            "斗南鎮": 0.1,
            "東勢鄉": 0,
            "林內鄉": 0.1,
            "水林鄉": 0.1,
            "莿桐鄉": 0.1,
            "虎尾鎮": 0.1,
            "褒忠鄉": 0,
            "西螺鎮": 0.1,
            "麥寮鄉": 0.1
        },
        "高雄市": {
            "三民區": 0.1,
            "仁武區": 0.1,
            "內門區": 0.1,
            "六龜區": 0.1,
            "前金區": 0.1,
            "前鎮區": 0.1,
            "大寮區": 0.1,
            "大樹區": 0.1,
            "大社區": 0.1,
            "小港區": 0.1,
            "岡山區": 0.1,
            "左營區": 0.1,
            "彌陀區": 0.1,
            "新興區": 0,
            "旗山區": 0.1,
            "旗津區": 0.1,
            "杉林區": 0.1,
            "林園區": 0.1,
            "桃源區": 0.1,
            "梓官區": 0.1,
            "楠梓區": 0.1,
            "橋頭區": 0.1,
            "永安區": 0.1,
            "湖內區": 0.1,
            "燕巢區": 0,
            "田寮區": 0.1,
            "甲仙區": 0.1,
            "美濃區": 0.1,
            "苓雅區": 0.1,
            "茂林區": 0.1,
            "茄萣區": 0,
            "路竹區": 0.1,
            "那瑪夏區": 0.1,
            "阿蓮區": 0.1,
            "鳥松區": 0.1,
            "鳳山區": 0.1,
            "鹽埕區": 0.1,
            "鼓山區": 0.1
        }
    },
    "increase": {
        "南投縣": {
            "中寮鄉": 29,
            "仁愛鄉": 64,
            "信義鄉": 59,
            "南投市": 350,
            "名間鄉": 105,
            "國姓鄉": 26,
            "埔里鎮": 210,
            "水里鄉": 49,
            "竹山鎮": 130,
            "草屯鎮": 259,
            "集集鎮": 21,
            "魚池鄉": 18,
            "鹿谷鄉": 32
        },
        "台中市": {
            "中區": 64,
            "北區": 508,
            "北屯區": 986,
            "南區": 431,
            "南屯區": 609,
            "后里區": 155,
            "和平區": 40,
            "外埔區": 79,
            "大安區": 50,
            "大甲區": 292,
            "大肚區": 221,
            "大里區": 850,
            "大雅區": 436,
            "太平區": 814,
            "新社區": 55,
            "東勢區": 116,
            "東區": 296,
            "梧棲區": 380,
            "沙鹿區": 426,
            "清水區": 377,
            "潭子區": 433,
            "烏日區": 347,
            "石岡區": 30,
            "神岡區": 190,
            "西區": 372,
            "西屯區": 921,
            "豐原區": 581,
            "霧峰區": 299,
            "龍井區": 335
        },
        "台北市": {
            "中山區": 522,
            "中正區": 246,
            "信義區": 602,
            "內湖區": 744,
            "北投區": 674,
            "南港區": 383,
            "士林區": 649,
            "大同區": 279,
            "大安區": 587,
            "文山區": 682,
            "松山區": 511,
            "萬華區": 457
        },
        "台南市": {
            "七股區": 74,
            "下營區": 65,
            "中西區": 250,
            "仁德區": 393,
            "佳里區": 158,
            "六甲區": 93,
            "北區": 469,
            "北門區": 25,
            "南化區": 13,
            "南區": 423,
            "善化區": 171,
            "大內區": 28,
            "學甲區": 61,
            "安南區": 688,
            "安定區": 85,
            "安平區": 194,
            "官田區": 65,
            "將軍區": 59,
            "山上區": 18,
            "左鎮區": 17,
            "後壁區": 55,
            "新化區": 169,
            "新市區": 140,
            "新營區": 359,
            "東區": 649,
            "東山區": 37,
            "柳營區": 78,
            "楠西區": 30,
            "歸仁區": 229,
            "永康區": 898,
            "玉井區": 52,
            "白河區": 48,
            "西港區": 88,
            "關廟區": 180,
            "鹽水區": 73,
            "麻豆區": 159,
            "龍崎區": 7
        },
        "台東縣": {
            "卑南鄉": 46,
            "台東市": 524,
            "大武鄉": 14,
            "太麻里鄉": 28,
            "延平鄉": 21,
            "成功鎮": 26,
            "東河鄉": 11,
            "池上鄉": 23,
            "海端鄉": 18,
            "綠島鄉": 10,
            "蘭嶼鄉": 18,
            "達仁鄉": 5,
            "金峰鄉": 5,
            "長濱鄉": 20,
            "關山鎮": 37,
            "鹿野鄉": 21
        },
        "嘉義市": {
            "東區": 371,
            "西區": 401
        },
        "嘉義縣": {
            "中埔鄉": 94,
            "六腳鄉": 43,
            "大埔鄉": 9,
            "大林鎮": 108,
            "太保市": 70,
            "布袋鎮": 24,
            "新港鄉": 48,
            "朴子市": 93,
            "東石鄉": 30,
            "梅山鄉": 22,
            "民雄鄉": 216,
            "水上鄉": 146,
            "溪口鄉": 18,
            "番路鄉": 25,
            "竹崎鄉": 69,
            "義竹鄉": 23,
            "阿里山鄉": 21,
            "鹿草鄉": 52
        },
        "基隆市": {
            "七堵區": 229,
            "中山區": 238,
            "中正區": 259,
            "仁愛區": 156,
            "信義區": 258,
            "其他": 0,
            "安樂區": 342,
            "暖暖區": 152
        },
        "宜蘭縣": {
            "三星鄉": 67,
            "五結鄉": 143,
            "冬山鄉": 185,
            "南澳鄉": 49,
            "員山鄉": 125,
            "壯圍鄉": 63,
            "大同鄉": 43,
            "宜蘭市": 288,
            "礁溪鄉": 112,
            "羅東鎮": 269,
            "蘇澳鎮": 233,
            "頭城鎮": 92
        },
        "屏東縣": {
            "三地門鄉": 33,
            "九如鄉": 67,
            "佳冬鄉": 54,
            "來義鄉": 36,
            "內埔鄉": 169,
            "南州鄉": 32,
            "屏東市": 579,
            "崁頂鄉": 34,
            "恆春鎮": 95,
            "新園鄉": 129,
            "新埤鄉": 30,
            "春日鄉": 34,
            "東港鎮": 183,
            "枋寮鄉": 100,
            "枋山鄉": 9,
            "林邊鄉": 67,
            "泰武鄉": 45,
            "滿州鄉": 15,
            "潮州鎮": 203,
            "牡丹鄉": 23,
            "獅子鄉": 18,
            "琉球鄉": 7,
            "瑪家鄉": 36,
            "竹田鄉": 40,
            "萬丹鄉": 191,
            "萬巒鄉": 57,
            "車城鄉": 22,
            "里港鄉": 92,
            "長治鄉": 106,
            "霧台鄉": 7,
            "高樹鄉": 68,
            "鹽埔鄉": 91,
            "麟洛鄉": 50
        },
        "彰化縣": {
            "二林鎮": 167,
            "二水鄉": 33,
            "伸港鄉": 159,
            "北斗鎮": 97,
            "和美鎮": 498,
            "員林市": 559,
            "埔心鄉": 108,
            "埔鹽鄉": 91,
            "埤頭鄉": 71,
            "大城鄉": 80,
            "大村鄉": 183,
            "彰化市": 691,
            "永靖鄉": 88,
            "溪州鄉": 64,
            "溪湖鎮": 117,
            "田中鎮": 162,
            "田尾鄉": 86,
            "社頭鄉": 129,
            "福興鄉": 171,
            "秀水鄉": 60,
            "竹塘鄉": 29,
            "線西鄉": 72,
            "芬園鄉": 53,
            "花壇鄉": 205,
            "芳苑鄉": 92,
            "鹿港鎮": 422
        },
        "新北市": {
            "三峽區": 434,
            "三芝區": 77,
            "三重區": 1563,
            "中和區": 1509,
            "五股區": 375,
            "八里區": 157,
            "土城區": 1020,
            "坪林區": 12,
            "平溪區": 1,
            "新店區": 1008,
            "新莊區": 1879,
            "板橋區": 1929,
            "林口區": 307,
            "樹林區": 670,
            "永和區": 695,
            "汐止區": 739,
            "泰山區": 329,
            "淡水區": 644,
            "深坑區": 99,
            "烏來區": 24,
            "瑞芳區": 126,
            "石碇區": 13,
            "石門區": 5,
            "萬里區": 56,
            "蘆洲區": 717,
            "貢寮區": 13,
            "金山區": 26,
            "雙溪區": 21,
            "鶯歌區": 378
        },
        "新竹市": {
            "北區": 544,
            "東區": 903,
            "香山區": 348
        },
        "新竹縣": {
            "五峰鄉": 9,
            "北埔鄉": 22,
            "寶山鄉": 37,
            "尖石鄉": 37,
            "峨眉鄉": 11,
            "新埔鎮": 77,
            "新豐鄉": 203,
            "橫山鄉": 34,
            "湖口鄉": 325,
            "竹北市": 758,
            "竹東鎮": 388,
            "芎林鄉": 84,
            "關西鎮": 77
        },
        "桃園市": {
            "中壢區": 1385,
            "八德區": 678,
            "大園區": 249,
            "大溪區": 614,
            "平鎮區": 740,
            "復興區": 79,
            "新屋區": 152,
            "桃園區": 1604,
            "楊梅區": 692,
            "蘆竹區": 530,
            "觀音區": 182,
            "龍潭區": 449,
            "龜山區": 706
        },
        "澎湖縣": {
            "七美鄉": 5,
            "望安鄉": 3,
            "湖西鄉": 19,
            "白沙鄉": 4,
            "西嶼鄉": 9,
            "馬公市": 151
        },
        "花蓮縣": {
            "光復鄉": 45,
            "卓溪鄉": 24,
            "吉安鄉": 275,
            "壽豐鄉": 76,
            "富里鄉": 35,
            "新城鄉": 81,
            "玉里鎮": 206,
            "瑞穗鄉": 37,
            "秀林鄉": 87,
            "花蓮市": 322,
            "萬榮鄉": 20,
            "豐濱鄉": 10,
            "鳳林鎮": 28
        },
        "苗栗縣": {
            "三灣鄉": 16,
            "三義鄉": 49,
            "公館鄉": 81,
            "卓蘭鎮": 25,
            "南庄鄉": 51,
            "大湖鄉": 12,
            "後龍鎮": 147,
            "泰安鄉": 30,
            "獅潭鄉": 4,
            "竹南鎮": 355,
            "苑裡鎮": 114,
            "苗栗市": 244,
            "西湖鄉": 7,
            "通霄鎮": 116,
            "造橋鄉": 81,
            "銅鑼鄉": 49,
            "頭份市": 438,
            "頭屋鄉": 40
        },
        "連江縣": {
            "北竿鄉": 3,
            "南竿鄉": 6,
            "東引鄉": 0,
            "莒光鄉": 0
        },
        "金門縣": {
            "烈嶼鄉": 11,
            "烏坵鄉": 0,
            "金城鎮": 42,
            "金寧鄉": 24,
            "金沙鎮": 30,
            "金湖鎮": 50
        },
        "雲林縣": {
            "二崙鄉": 44,
            "元長鄉": 85,
            "北港鎮": 91,
            "口湖鄉": 26,
            "古坑鄉": 70,
            "台西鄉": 19,
            "四湖鄉": 39,
            "土庫鎮": 70,
            "大埤鄉": 27,
            "崙背鄉": 47,
            "斗六市": 320,
            "斗南鎮": 80,
            "東勢鄉": 8,
            "林內鄉": 57,
            "水林鄉": 37,
            "莿桐鄉": 60,
            "虎尾鎮": 229,
            "褒忠鄉": 10,
            "西螺鎮": 128,
            "麥寮鄉": 71
        },
        "高雄市": {
            "三民區": 1214,
            "仁武區": 387,
            "內門區": 40,
            "六龜區": 38,
            "前金區": 149,
            "前鎮區": 733,
            "大寮區": 523,
            "大樹區": 137,
            "大社區": 208,
            "小港區": 634,
            "岡山區": 396,
            "左營區": 671,
            "彌陀區": 68,
            "新興區": 123,
            "旗山區": 77,
            "旗津區": 149,
            "杉林區": 25,
            "林園區": 297,
            "桃源區": 16,
            "梓官區": 164,
            "楠梓區": 946,
            "橋頭區": 158,
            "永安區": 27,
            "湖內區": 116,
            "燕巢區": 142,
            "田寮區": 22,
            "甲仙區": 10,
            "美濃區": 72,
            "苓雅區": 639,
            "茂林區": 5,
            "茄萣區": 59,
            "路竹區": 213,
            "那瑪夏區": 11,
            "阿蓮區": 89,
            "鳥松區": 118,
            "鳳山區": 1405,
            "鹽埕區": 61,
            "鼓山區": 542
        }
    },
    "avg7": {
        "南投縣": {
            "中寮鄉": 21.9,
            "仁愛鄉": 55.3,
            "信義鄉": 38.4,
            "南投市": 304.6,
            "名間鄉": 81.9,
            "國姓鄉": 34.9,
            "埔里鎮": 155.7,
            "水里鄉": 27.1,
            "竹山鎮": 110.6,
            "草屯鎮": 210,
            "集集鎮": 12.1,
            "魚池鄉": 15.6,
            "鹿谷鄉": 22
        },
        "台中市": {
            "中區": 61.1,
            "北區": 481.7,
            "北屯區": 831.9,
            "南區": 434.7,
            "南屯區": 550.3,
            "后里區": 144,
            "和平區": 28.6,
            "外埔區": 89.1,
            "大安區": 50,
            "大甲區": 247.3,
            "大肚區": 187.1,
            "大里區": 750.1,
            "大雅區": 359,
            "太平區": 772,
            "新社區": 45.1,
            "東勢區": 123.9,
            "東區": 254.7,
            "梧棲區": 306.9,
            "沙鹿區": 400.7,
            "清水區": 322.1,
            "潭子區": 370,
            "烏日區": 311.4,
            "石岡區": 27.6,
            "神岡區": 213,
            "西區": 350.7,
            "西屯區": 863.6,
            "豐原區": 509.7,
            "霧峰區": 245.9,
            "龍井區": 287.7
        },
        "台北市": {
            "中山區": 608.1,
            "中正區": 306,
            "信義區": 636.4,
            "內湖區": 885.1,
            "北投區": 753.7,
            "南港區": 403,
            "士林區": 718.1,
            "大同區": 350.4,
            "大安區": 590.6,
            "文山區": 717.9,
            "松山區": 501.4,
            "萬華區": 555
        },
        "台南市": {
            "七股區": 49.3,
            "下營區": 44.1,
            "中西區": 208.4,
            "仁德區": 289.4,
            "佳里區": 172.7,
            "六甲區": 57.6,
            "北區": 444.7,
            "北門區": 11.4,
            "南化區": 9.1,
            "南區": 402.4,
            "善化區": 179.9,
            "大內區": 19.6,
            "學甲區": 48.4,
            "安南區": 712.6,
            "安定區": 86.6,
            "安平區": 199.3,
            "官田區": 53.6,
            "將軍區": 36,
            "山上區": 20.7,
            "左鎮區": 17.6,
            "後壁區": 38.1,
            "新化區": 152.9,
            "新市區": 161,
            "新營區": 259,
            "東區": 516.9,
            "東山區": 26.3,
            "柳營區": 74.9,
            "楠西區": 13.1,
            "歸仁區": 214.7,
            "永康區": 1012.6,
            "玉井區": 26.6,
            "白河區": 33.1,
            "西港區": 74.3,
            "關廟區": 137.9,
            "鹽水區": 55,
            "麻豆區": 124.3,
            "龍崎區": 5.4
        },
        "台東縣": {
            "卑南鄉": 44.7,
            "台東市": 438.1,
            "大武鄉": 11.7,
            "太麻里鄉": 28.6,
            "延平鄉": 17.4,
            "成功鎮": 30.9,
            "東河鄉": 16.6,
            "池上鄉": 14.7,
            "海端鄉": 17.6,
            "綠島鄉": 7.1,
            "蘭嶼鄉": 21.3,
            "達仁鄉": 4.6,
            "金峰鄉": 9.4,
            "長濱鄉": 16.3,
            "關山鎮": 28.1,
            "鹿野鄉": 19.1
        },
        "嘉義市": {
            "東區": 265.7,
            "西區": 306.9
        },
        "嘉義縣": {
            "中埔鄉": 92.1,
            "六腳鄉": 34.7,
            "大埔鄉": 3.9,
            "大林鎮": 80.6,
            "太保市": 80.4,
            "布袋鎮": 31.6,
            "新港鄉": 48.7,
            "朴子市": 84.1,
            "東石鄉": 16,
            "梅山鄉": 26.3,
            "民雄鄉": 186.7,
            "水上鄉": 120.3,
            "溪口鄉": 19.4,
            "番路鄉": 14.7,
            "竹崎鄉": 47.7,
            "義竹鄉": 24.3,
            "阿里山鄉": 10.3,
            "鹿草鄉": 34.4
        },
        "基隆市": {
            "七堵區": 241.6,
            "中山區": 184.3,
            "中正區": 224,
            "仁愛區": 175.4,
            "信義區": 227.6,
            "其他": 0,
            "安樂區": 365.6,
            "暖暖區": 155.6
        },
        "宜蘭縣": {
            "三星鄉": 82.6,
            "五結鄉": 129.9,
            "冬山鄉": 194.3,
            "南澳鄉": 32.6,
            "員山鄉": 109.3,
            "壯圍鄉": 75.7,
            "大同鄉": 44.9,
            "宜蘭市": 308.3,
            "礁溪鄉": 125.4,
            "羅東鎮": 259.3,
            "蘇澳鎮": 195.4,
            "頭城鎮": 82.1
        },
        "屏東縣": {
            "三地門鄉": 27.7,
            "九如鄉": 53.6,
            "佳冬鄉": 37.3,
            "來義鄉": 39,
            "內埔鄉": 167.3,
            "南州鄉": 29,
            "屏東市": 624.4,
            "崁頂鄉": 23.9,
            "恆春鎮": 85.3,
            "新園鄉": 130.6,
            "新埤鄉": 28.6,
            "春日鄉": 24.3,
            "東港鎮": 197.7,
            "枋寮鄉": 66.9,
            "枋山鄉": 7.4,
            "林邊鄉": 38.6,
            "泰武鄉": 26.1,
            "滿州鄉": 14,
            "潮州鎮": 198.6,
            "牡丹鄉": 16,
            "獅子鄉": 12.9,
            "琉球鄉": 8.6,
            "瑪家鄉": 30.4,
            "竹田鄉": 36.1,
            "萬丹鄉": 154.4,
            "萬巒鄉": 49.6,
            "車城鄉": 18.4,
            "里港鄉": 60.6,
            "長治鄉": 103.3,
            "霧台鄉": 6,
            "高樹鄉": 38.6,
            "鹽埔鄉": 63.3,
            "麟洛鄉": 33.1
        },
        "彰化縣": {
            "二林鎮": 162.3,
            "二水鄉": 22.3,
            "伸港鄉": 113.6,
            "北斗鎮": 100.3,
            "和美鎮": 318.4,
            "員林市": 367.4,
            "埔心鄉": 101.1,
            "埔鹽鄉": 66,
            "埤頭鄉": 68,
            "大城鄉": 43.6,
            "大村鄉": 132.9,
            "彰化市": 687.7,
            "永靖鄉": 80.9,
            "溪州鄉": 55.4,
            "溪湖鎮": 119.7,
            "田中鎮": 104.4,
            "田尾鄉": 54.4,
            "社頭鄉": 96.9,
            "福興鄉": 135.4,
            "秀水鄉": 85.4,
            "竹塘鄉": 24.7,
            "線西鄉": 50,
            "芬園鄉": 57.9,
            "花壇鄉": 137.6,
            "芳苑鄉": 78.6,
            "鹿港鎮": 347.1
        },
        "新北市": {
            "三峽區": 466.7,
            "三芝區": 57.7,
            "三重區": 1949.1,
            "中和區": 1808,
            "五股區": 405.3,
            "八里區": 158.6,
            "土城區": 1086.6,
            "坪林區": 10.6,
            "平溪區": 4.7,
            "新店區": 1148.4,
            "新莊區": 2127.6,
            "板橋區": 2427.9,
            "林口區": 437.7,
            "樹林區": 748.7,
            "永和區": 832.3,
            "汐止區": 968.6,
            "泰山區": 357.4,
            "淡水區": 682.1,
            "深坑區": 98,
            "烏來區": 18.1,
            "瑞芳區": 107.6,
            "石碇區": 11.3,
            "石門區": 9,
            "萬里區": 54.6,
            "蘆洲區": 846.7,
            "貢寮區": 11.4,
            "金山區": 40,
            "雙溪區": 11.3,
            "鶯歌區": 399
        },
        "新竹市": {
            "北區": 520.1,
            "東區": 920.9,
            "香山區": 324
        },
        "新竹縣": {
            "五峰鄉": 12.9,
            "北埔鄉": 14.7,
            "寶山鄉": 46.1,
            "尖石鄉": 30.3,
            "峨眉鄉": 9.7,
            "新埔鎮": 92.9,
            "新豐鄉": 251.3,
            "橫山鄉": 32.4,
            "湖口鄉": 478.9,
            "竹北市": 758.1,
            "竹東鎮": 436.3,
            "芎林鄉": 71.7,
            "關西鎮": 81.4
        },
        "桃園市": {
            "中壢區": 1757.7,
            "八德區": 812.9,
            "大園區": 338.6,
            "大溪區": 426.7,
            "平鎮區": 961,
            "復興區": 60.4,
            "新屋區": 202,
            "桃園區": 1704.4,
            "楊梅區": 734.4,
            "蘆竹區": 570.9,
            "觀音區": 298,
            "龍潭區": 542.1,
            "龜山區": 807.9
        },
        "澎湖縣": {
            "七美鄉": 4.4,
            "望安鄉": 1.1,
            "湖西鄉": 19.3,
            "白沙鄉": 3.7,
            "西嶼鄉": 4.1,
            "馬公市": 103
        },
        "花蓮縣": {
            "光復鄉": 44.7,
            "卓溪鄉": 28.7,
            "吉安鄉": 318.7,
            "壽豐鄉": 65.9,
            "富里鄉": 28.6,
            "新城鄉": 103.7,
            "玉里鎮": 145.6,
            "瑞穗鄉": 32.9,
            "秀林鄉": 101.7,
            "花蓮市": 337.1,
            "萬榮鄉": 21,
            "豐濱鄉": 7.4,
            "鳳林鎮": 31.4
        },
        "苗栗縣": {
            "三灣鄉": 18.1,
            "三義鄉": 35.3,
            "公館鄉": 74.1,
            "卓蘭鎮": 35.7,
            "南庄鄉": 36.9,
            "大湖鄉": 17.9,
            "後龍鎮": 100.4,
            "泰安鄉": 23.3,
            "獅潭鄉": 3.9,
            "竹南鎮": 392.4,
            "苑裡鎮": 162.1,
            "苗栗市": 225.1,
            "西湖鄉": 10,
            "通霄鎮": 122.1,
            "造橋鄉": 73.1,
            "銅鑼鄉": 40,
            "頭份市": 432.7,
            "頭屋鄉": 27.7
        },
        "連江縣": {
            "北竿鄉": 4.7,
            "南竿鄉": 19.1,
            "東引鄉": 0,
            "莒光鄉": 0
        },
        "金門縣": {
            "烈嶼鄉": 6.3,
            "烏坵鄉": 0,
            "金城鎮": 31.6,
            "金寧鄉": 29.9,
            "金沙鎮": 18.3,
            "金湖鎮": 30
        },
        "雲林縣": {
            "二崙鄉": 35.6,
            "元長鄉": 45.9,
            "北港鎮": 69.6,
            "口湖鄉": 30.6,
            "古坑鄉": 57.6,
            "台西鄉": 24.3,
            "四湖鄉": 21.9,
            "土庫鎮": 55.3,
            "大埤鄉": 28.3,
            "崙背鄉": 41,
            "斗六市": 279.3,
            "斗南鎮": 102,
            "東勢鄉": 13.6,
            "林內鄉": 42.6,
            "水林鄉": 24.9,
            "莿桐鄉": 54.9,
            "虎尾鎮": 186,
            "褒忠鄉": 13.7,
            "西螺鎮": 108.3,
            "麥寮鄉": 67.4
        },
        "高雄市": {
            "三民區": 1182.7,
            "仁武區": 322.9,
            "內門區": 34.6,
            "六龜區": 22.6,
            "前金區": 160.4,
            "前鎮區": 674.6,
            "大寮區": 430.9,
            "大樹區": 129,
            "大社區": 133.9,
            "小港區": 775.4,
            "岡山區": 365,
            "左營區": 573,
            "彌陀區": 62.7,
            "新興區": 143.3,
            "旗山區": 72.1,
            "旗津區": 110.1,
            "杉林區": 20.6,
            "林園區": 241.3,
            "桃源區": 14,
            "梓官區": 149.6,
            "楠梓區": 863.1,
            "橋頭區": 126.6,
            "永安區": 28.9,
            "湖內區": 97.6,
            "燕巢區": 168.9,
            "田寮區": 14.7,
            "甲仙區": 8.1,
            "美濃區": 63.3,
            "苓雅區": 573.6,
            "茂林區": 4.3,
            "茄萣區": 91.6,
            "路竹區": 217.1,
            "那瑪夏區": 12.4,
            "阿蓮區": 84,
            "鳥松區": 126.6,
            "鳳山區": 1372.1,
            "鹽埕區": 65.9,
            "鼓山區": 405.3
        }
    }
}