{
    "city": "嘉義縣",
    "area": "大林鎮",
    "days": {
        "20230223": 9,
        "20230224": 13,
        "20230225": 14,
        "20230226": 8,
        "20230227": 5,
        "20230228": 14,
        "20230301": 16,
        "20230302": 6,
        "20230303": 8,
        "20230304": 15,
        "20230305": 7,
        "20230306": 7,
        "20230307": 16,
        "20230308": 11,
        "20230309": 4,
        "20230310": 10,
        "20230311": 13,
        "20230312": 6,
        "20230313": 14,
        "20230314": 9,
        "20230315": 17,
        "20230316": 9,
        "20230317": 13,
        "20230318": 14,
        "20230319": 9,
        "20230320": 2,
        "20230321": 0,
        "20230322": 0,
        "20230323": 0,
        "20230324": 0,
        "20230325": 0,
        "20230326": 0,
        "20230327": 0,
        "20230328": 0,
        "20230329": 0,
        "20230330": 0,
        "20230331": 0,
        "20230401": 0,
        "20230402": 0,
        "20230403": 0,
        "20230404": 0,
        "20230405": 0,
        "20230406": 0,
        "20230407": 0,
        "20230408": 0,
        "20230409": 0,
        "20230410": 0,
        "20230411": 0,
        "20230412": 0,
        "20230413": 0,
        "20230414": 0,
        "20230415": 0,
        "20230416": 0,
        "20230417": 0,
        "20230418": 0,
        "20230419": 0,
        "20230420": 0,
        "20230421": 0
    },
    "gender": {
        "m": 121,
        "f": 148
    },
    "age": {
        "0": 2,
        "1": 1,
        "2": 2,
        "3": 0,
        "4": 0,
        "5-9": 15,
        "10-14": 10,
        "15-19": 13,
        "20-24": 24,
        "25-29": 30,
        "30-34": 19,
        "35-39": 22,
        "40-44": 28,
        "45-49": 18,
        "50-54": 11,
        "55-59": 15,
        "60-64": 13,
        "65-69": 13,
        "70+": 33
    }
}