{
    "city": "屏東縣",
    "area": "內埔鄉",
    "days": {
        "20230216": 41,
        "20230217": 23,
        "20230218": 26,
        "20230219": 19,
        "20230220": 50,
        "20230221": 30,
        "20230222": 36,
        "20230223": 32,
        "20230224": 28,
        "20230225": 22,
        "20230226": 12,
        "20230227": 24,
        "20230228": 31,
        "20230301": 36,
        "20230302": 43,
        "20230303": 22,
        "20230304": 20,
        "20230305": 19,
        "20230306": 39,
        "20230307": 36,
        "20230308": 28,
        "20230309": 23,
        "20230310": 24,
        "20230311": 19,
        "20230312": 14,
        "20230313": 34,
        "20230314": 34,
        "20230315": 19,
        "20230316": 20,
        "20230317": 29,
        "20230318": 31,
        "20230319": 15,
        "20230320": 2,
        "20230321": 1,
        "20230322": 1,
        "20230323": 0,
        "20230324": 0,
        "20230325": 0,
        "20230326": 0,
        "20230327": 0,
        "20230328": 0,
        "20230329": 0,
        "20230330": 0,
        "20230331": 0,
        "20230401": 0,
        "20230402": 0,
        "20230403": 0,
        "20230404": 0,
        "20230405": 0,
        "20230406": 0,
        "20230407": 0,
        "20230408": 0,
        "20230409": 0,
        "20230410": 0,
        "20230411": 0,
        "20230412": 0,
        "20230413": 0,
        "20230414": 0
    },
    "gender": {
        "m": 414,
        "f": 469
    },
    "age": {
        "0": 11,
        "1": 9,
        "2": 8,
        "3": 8,
        "4": 6,
        "5-9": 23,
        "10-14": 31,
        "15-19": 53,
        "20-24": 106,
        "25-29": 83,
        "30-34": 55,
        "35-39": 59,
        "40-44": 49,
        "45-49": 41,
        "50-54": 44,
        "55-59": 65,
        "60-64": 56,
        "65-69": 55,
        "70+": 121
    }
}