{
    "city": "桃園市",
    "area": "蘆竹區",
    "days": {
        "20230305": 66,
        "20230306": 84,
        "20230307": 104,
        "20230308": 78,
        "20230309": 72,
        "20230310": 72,
        "20230311": 95,
        "20230312": 58,
        "20230313": 70,
        "20230314": 78,
        "20230315": 69,
        "20230316": 82,
        "20230317": 61,
        "20230318": 64,
        "20230319": 54,
        "20230320": 26,
        "20230321": 1,
        "20230322": 0,
        "20230323": 0,
        "20230324": 0,
        "20230325": 0,
        "20230326": 0,
        "20230327": 0,
        "20230328": 0,
        "20230329": 0,
        "20230330": 0,
        "20230331": 0,
        "20230401": 0,
        "20230402": 0,
        "20230403": 0,
        "20230404": 0,
        "20230405": 0,
        "20230406": 0,
        "20230407": 0,
        "20230408": 0,
        "20230409": 0,
        "20230410": 0,
        "20230411": 0,
        "20230412": 0,
        "20230413": 0,
        "20230414": 0,
        "20230415": 0,
        "20230416": 0,
        "20230417": 0,
        "20230418": 0,
        "20230419": 0,
        "20230420": 0,
        "20230421": 0,
        "20230422": 0,
        "20230423": 0,
        "20230424": 0,
        "20230425": 0,
        "20230426": 0,
        "20230427": 0,
        "20230428": 0,
        "20230429": 0,
        "20230430": 0,
        "20230501": 0,
        "20230502": 0,
        "20230503": 0
    },
    "gender": {
        "m": 553,
        "f": 581
    },
    "age": {
        "0": 10,
        "1": 10,
        "2": 11,
        "3": 6,
        "4": 7,
        "5-9": 79,
        "10-14": 59,
        "15-19": 78,
        "20-24": 80,
        "25-29": 118,
        "30-34": 90,
        "35-39": 94,
        "40-44": 108,
        "45-49": 92,
        "50-54": 74,
        "55-59": 74,
        "60-64": 45,
        "65-69": 34,
        "70+": 65
    }
}