{
    "city": "高雄市",
    "area": "杉林區",
    "days": {
        "20220407": 0,
        "20220408": 0,
        "20220409": 0,
        "20220410": 0,
        "20220411": 0,
        "20220412": 0,
        "20220413": 0,
        "20220414": 0,
        "20220415": 0,
        "20220416": 0,
        "20220417": 0,
        "20220418": 1,
        "20220419": 0,
        "20220420": 0,
        "20220421": 0,
        "20220422": 0,
        "20220423": 0,
        "20220424": 0,
        "20220425": 1,
        "20220426": 0,
        "20220427": 0,
        "20220428": 1,
        "20220429": 0,
        "20220430": 0,
        "20220501": 0,
        "20220502": 1,
        "20220503": 3,
        "20220504": 0,
        "20220505": 1,
        "20220506": 10,
        "20220507": 5,
        "20220508": 14,
        "20220509": 5,
        "20220510": 13,
        "20220511": 8,
        "20220512": 10,
        "20220513": 7,
        "20220514": 8,
        "20220515": 4,
        "20220516": 13,
        "20220517": 20,
        "20220518": 10,
        "20220519": 13,
        "20220520": 12,
        "20220521": 11,
        "20220522": 13,
        "20220523": 9,
        "20220524": 14,
        "20220525": 21,
        "20220526": 23,
        "20220527": 21,
        "20220528": 20,
        "20220529": 20,
        "20220530": 28,
        "20220531": 39,
        "20220601": 28,
        "20220602": 42,
        "20220603": 24,
        "20220604": 26
    },
    "gender": {
        "m": 238,
        "f": 261
    },
    "age": {
        "0": 4,
        "1": 6,
        "2": 4,
        "3": 10,
        "4": 7,
        "5-9": 45,
        "10-14": 31,
        "15-19": 28,
        "20-24": 38,
        "25-29": 52,
        "30-34": 25,
        "35-39": 28,
        "40-44": 37,
        "45-49": 29,
        "50-54": 34,
        "55-59": 30,
        "60-64": 28,
        "65-69": 20,
        "70+": 43
    }
}